Workbook

Sheet README
A1: ⚠ SIMULATED FINANCIAL INFORMATION - illustrative Calgary management accounts, not Prairie Pulse E-Bikes' actual financials. Synthetic data generated for a VisiVault Analytics proof of concept (seed 20240101).
A2: Prairie Pulse E-Bikes - Integrated Three-Statement Financial Model (illustrative)
A3: Prepared by VisiVault Analytics Ltd. | Proof of concept | October 2026
A5: WHAT THIS IS
A6: Illustrative Calgary branch MANAGEMENT ACCOUNTS (not consolidated corporate statements), built by double entry from synthetic operational data.
A7: Historical months (Jan-2024 to Sep-2026) are SIMULATED actuals from the general ledger; Oct-2026 to Sep-2027 are FORECASTS.
A8: No figure describes Prairie Pulse E-Bikes' actual financial position, results or cash flows.
A10: HOW TO USE
A11: 1. Assumptions!C4 - choose Conservative / Base / Optimistic / Custom (edit the Custom column freely).
A12: 2. Drivers - edit any blue monthly input (volumes, staffing plan, marketing plan, capex plan, inventory cover policy).
A13: 3. Forecast - three statements recalculate; the CHECKS rows and the Checks sheet must stay at 0 / TRUE.
A14: 4. Scenario_Results - stored comparison of the three scenarios and the sensitivity analysis.
... A29: Imputed inventory financing cost in the operational dataset is excluded; actual interest on the allocated debt is charged instead.

Sheet Assumptions
A1: ⚠ SIMULATED FINANCIAL INFORMATION - illustrative Calgary management accounts, not Prairie Pulse E-Bikes' actual financials. Synthetic data generated for a VisiVault Analytics proof of concept (seed 20240101).
A2: Forecast assumptions - choose a scenario, or edit the Custom column
A3: Blue cells on yellow are inputs. Column H (Active) feeds every forecast formula.
B4: Active scenario >> | C4: Base
A7: Key | B7: Scenario driver | C7: Unit | D7: Conservative | E7: Base | F7: Optimistic | G7: Custom | H7: Active
A8: demand_mult | B8: Demand multiplier (bikes & accessories) | C8: x | D8: 0.92 | E8: 1 | F8: 1.06 | G8: 1 | H8: =INDEX(D8:G8,MATCH($C$4,$D$7:$G$7,0)) -> 1
A9: price_change | B9: List-price change | C9: % | D9: 0 | E9: 0 | F9: 0.02 | G9: 0 | H9: =INDEX(D9:G9,MATCH($C$4,$D$7:$G$7,0)) -> 0
A10: elasticity | B10: Price elasticity of bike units | C10: x | D10: -1.2 | E10: -1.2 | F10: -1.2 | G10: -1.2 | H10: =INDEX(D10:G10,MATCH($C$4,$D$7:$G$7,0)) -> -1.2
A11: discount_delta | B11: Change in bike discount rate | C11: pts | D11: 0.01 | E11: 0 | F11: -0.01 | G11: 0 | H11: =INDEX(D11:G11,MATCH($C$4,$D$7:$G$7,0)) -> 0
A12: margin_pts | B12: Merchandise gross-margin improvement | C12: pts | D12: 0 | E12: 0 | F12: 0.01 | G12: 0 | H12: =INDEX(D12:G12,MATCH($C$4,$D$7:$G$7,0)) -> 0
A13: supplier_cost | B13: Supplier / inventory cost change | C13: % | D13: 0.03 | E13: 0 | F13: 0 | G13: 0 | H13: =INDEX(D13:G13,MATCH($C$4,$D$7:$G$7,0)) -> 0
A14: service_mult | B14: Service revenue multiplier | C14: x | D14: 0.97 | E14: 1 | F14: 1.1 | G14: 1 | H14: =INDEX(D14:G14,MATCH($C$4,$D$7:$G$7,0)) -> 1
A15: dpo_delta | B15: Change in supplier payment days | C15: days | D15: -5 | E15: 0 | F15: 5 | G15: 0 | H15: =INDEX(D15:G15,MATCH($C$4,$D$7:$G$7,0)) -> 0
A16: rate_delta | B16: Change in prime rate | C16: % | D16: 0.005 | E16: 0 | F16: -0.0025 | G16: 0 | H16: =INDEX(D16:G16,MATCH($C$4,$D$7:$G$7,0)) -> 0
A17: cover_mult | B17: Inventory cover policy multiplier | C17: x | D17: 1.05 | E17: 1 | F17: 0.9 | G17: 1 | H17: =INDEX(D17:G17,MATCH($C$4,$D$7:$G$7,0)) -> 1
B19: Scenario notes
B20: Conservative | C20: Demand -8%, supplier costs +3% (CAD/USD, tariffs), +1 pt discounting, service -3%, suppliers tighten terms by 5 days, prime +50 bps, slower sell-through (+5% cover).
B21: Base | C21: Model 1 (Prophet) volumes, TTM prices/discounts/costs, current staffing and lease schedule, current working-capital ratios, prime flat at 4.45%.
B22: Optimistic | C22: Demand +6%, +2% list price, -1 pt discounting, +1 pt merchandise margin, service +10%, +5 supplier days, prime -25 bps, leaner inventory (-10% cover).
A24: Key | B24: Calibrated / policy parameter (TTM Oct-2025 to Sep-2026 unless stated) | H24: Value
A25: asp_list | B25: Average e-bike list price (TTM) | H25: 2591.8897
A26: d_b | B26: Bike discount rate (TTM) | H26: 0.023285991
A27: r_b | B27: Bike return rate (TTM, % of net) | H27: 0.030389597
A28: d_a | B28: Accessory discount rate (TTM) | H28: 0.021077569
A29: r_a | B29: Accessory return rate (TTM) | H29: 0.034576939
A30: uc_bike | B30: Average e-bike unit cost (TTM) | H30: 1823.2822
A31: c_a | B31: Accessory COGS ratio (TTM) | H31: 0.58217788
A32: shrink_rate | B32: Shrinkage & write-offs, % of merchandise COGS | H32: 0.004024491
A33: parts_ratio | B33: Service parts cost, % of service revenue | H33: 0.21962052
A34: labour_ratio | B34: Direct service labour, % of service revenue | H34: 0.16953808
A35: comm_rate | B35: Sales commission on net bike revenue | H35: 0.015
A36: freight_rate | B36: Freight, % of inventory purchases | H36: 0.037952418
... A59: corp_alloc | B59: Corporate shared-services allocation / month | H59: 650

Sheet Drivers
A1: ⚠ SIMULATED FINANCIAL INFORMATION - illustrative Calgary management accounts, not Prairie Pulse E-Bikes' actual financials. Synthetic data generated for a VisiVault Analytics proof of concept (seed 20240101).
A2: Monthly drivers (inputs) - base volumes from Model 1, staffing plan, lease, marketing plan, capex plan, inventory policy
A3: Edit any blue cell; the forecast recalculates. Column C = actual 30-Sep-2026 position (not used by drivers).
A5: Key | B5: Line | C5: Sep-2026 actual | D5: Oct-2026 | E5: Nov-2026 | F5: Dec-2026 | G5: Jan-2027 | H5: Feb-2027 | I5: Mar-2027 | J5: Apr-2027 | K5: May-2027 | L5: Jun-2027 | M5: Jul-2027 | N5: Aug-2027 | O5: Sep-2027 | P5: 12-month total
A6: units_base | B6: E-bike units - Model 1 Prophet base forecast | D6: 50.433529 | E6: 37.28996 | F6: 31.442638 | G6: 23.546461 | H6: 22.673747 | I6: 49.435386 | J6: 111.31885 | K6: 132.99826 | L6: 128.73152 | M6: 121.48594 | N6: 105.9684 | O6: 74.610759
A7: acc_net_base | B7: Net accessories & parts revenue - Model 1 base (retail less bikes) | D7: 22723.518 | E7: 12180.322 | F7: 15285.082 | G7: 15178.059 | H7: 11141.182 | I7: 20438.756 | J7: 28791.859 | K7: 36900.546 | L7: 51068.195 | M7: 38132.029 | N7: 34732.495 | O7: 28765.636
A8: svc_base | B8: Service revenue - Model 1 Prophet base forecast | D8: 47493.619 | E8: 27826.365 | F8: 22788.956 | G8: 36907.954 | H8: 43967.133 | I8: 62422.863 | J8: 83178.978 | K8: 89350.198 | L8: 91001.053 | M8: 77401.867 | N8: 64221.754 | O8: 59638.215
A9: staff_payroll | B9: Sales, management & admin payroll (excl. commission) - staffing plan | D9: 21791.505 | E9: 20718.66 | F9: 20718.66 | G9: 21791.501 | H9: 20182.232 | I9: 21791.508 | J9: 29041.879 | K9: 29041.879 | L9: 29889.774 | M9: 29889.773 | N9: 29889.781 | O9: 29041.878
A10: tech_payroll | B10: Technician payroll capacity - staffing plan | D10: 17184.726 | E10: 15862.824 | F10: 15862.824 | G10: 17184.726 | H10: 15201.873 | I10: 17184.726 | J10: 26762.294 | K10: 26762.294 | L10: 27832.784 | M10: 27832.784 | N10: 27832.784 | O10: 26762.294
A11: rent_d | B11: Rent - lease schedule (3% escalation each January) | D11: 20157.1 | E11: 20157.1 | F11: 20157.1 | G11: 20761.813 | H11: 20761.813 | I11: 20761.813 | J11: 20761.813 | K11: 20761.813 | L11: 20761.813 | M11: 20761.813 | N11: 20761.813 | O11: 20761.813
A12: utilities_d | B12: Utilities - seasonal TTM +2.5% | D12: 1546.8788 | E12: 1857.054 | F12: 2290.4138 | G12: 2197.1695 | H12: 2085.834 | I12: 1961.932 | J12: 1760.9398 | K12: 1216.7877 | L12: 1299.3412 | M12: 1198.6043 | N12: 1079.0585 | O12: 1240.168
A13: marketing_d | B13: Marketing plan - seasonal TTM +6% | D13: 5903.9668 | E13: 5074.008 | F13: 5157.6738 | G13: 5029.859 | H13: 5430.009 | I13: 6559.4602 | J13: 8211.979 | K13: 10437.502 | L13: 10167.626 | M13: 9170.8656 | N13: 8276.5542 | O13: 8066.0382
A14: insurance_exp | B14: Insurance expense - policy schedule | D14: 2487.68 | E14: 2487.68 | F14: 2487.68 | G14: 2587.1872 | H14: 2587.1872 | I14: 2587.1872 | J14: 2587.1872 | K14: 2587.1872 | L14: 2587.1872 | M14: 2587.1872 | N14: 2587.1872 | O14: 2587.1872
A15: insurance_premium | B15: Insurance premium paid (January) | D15: 0 | E15: 0 | F15: 0 | G15: 31046.246 | H15: 0 | I15: 0 | J15: 0 | K15: 0 | L15: 0 | M15: 0 | N15: 0 | O15: 0
A16: admin_local | B16: Local administrative costs | D16: 3221.3452 | E16: 3221.3452 | F16: 3221.3452 | G16: 3221.3452 | H16: 3221.3452 | I16: 3221.3452 | J16: 3221.3452 | K16: 3221.3452 | L16: 3221.3452 | M16: 3221.3452 | N16: 3221.3452 | O16: 3221.3452
A17: capex_d | B17: Capital expenditure plan | D17: 0 | E17: 0 | F17: 0 | G17: 6000 | H17: 0 | I17: 12000 | J17: 0 | K17: 0 | L17: 0 | M17: 0 | N17: 0 | O17: 0
... A23: q_start | B23: Flag: first month of quarter | D23: 1 | E23: 0 | F23: 0 | G23: 1 | H23: 0 | I23: 0 | J23: 1 | K23: 0 | L23: 0 | M23: 1 | N23: 0 | O23: 0

Sheet Forecast
A1: ⚠ SIMULATED FINANCIAL INFORMATION - illustrative Calgary management accounts, not Prairie Pulse E-Bikes' actual financials. Synthetic data generated for a VisiVault Analytics proof of concept (seed 20240101).
A2: Integrated 12-month forecast Oct-2026 to Sep-2027 (FORECAST - not historical fact)
A3: Every cell in columns D:O is a formula driven by Assumptions (active scenario) and Drivers. Column C links to the historical ledger.
A5: Key | B5: Line | C5: Sep-2026 actual | D5: Oct-2026 | E5: Nov-2026 | F5: Dec-2026 | G5: Jan-2027 | H5: Feb-2027 | I5: Mar-2027 | J5: Apr-2027 | K5: May-2027 | L5: Jun-2027 | M5: Jul-2027 | N5: Aug-2027 | O5: Sep-2027 | P5: 12-month total
A7: INCOME STATEMENT (forecast)
A8: bike_rev | B8: Bicycle sales revenue | D8: =D89*D90/(1-Assumptions!$H$27) -> 134815.12 | E8: =E89*E90/(1-Assumptions!$H$27) -> 99680.718 | F8: =F89*F90/(1-Assumptions!$H$27) -> 84050.099 | G8: =G89*G90/(1-Assumptions!$H$27) -> 62942.63 | H8: =H89*H90/(1-Assumptions!$H$27) -> 60609.756 | I8: =I89*I90/(1-Assumptions!$H$27) -> 132146.96 | J8: =J89*J90/(1-Assumptions!$H$27) -> 297569.19 | K8: =K89*K90/(1-Assumptions!$H$27) -> 355520.96 | ... O8: =O89*O90/(1-Assumptions!$H$27) -> 199443.87 | P8: =SUM(D8:O8) -> 2378908.6
A9: acc_rev | B9: Accessories and parts revenue | D9: =D93/((1-Assumptions!$H$28)*(1-Assumptions!$H$29)) -> 24044.16 | E9: =E93/((1-Assumptions!$H$28)*(1-Assumptions!$H$29)) -> 12888.216 | F9: =F93/((1-Assumptions!$H$28)*(1-Assumptions!$H$29)) -> 16173.419 | G9: =G93/((1-Assumptions!$H$28)*(1-Assumptions!$H$29)) -> 16060.176 | H9: =H93/((1-Assumptions!$H$28)*(1-Assumptions!$H$29)) -> 11788.684 | I9: =I93/((1-Assumptions!$H$28)*(1-Assumptions!$H$29)) -> 21626.613 | J9: =J93/((1-Assumptions!$H$28)*(1-Assumptions!$H$29)) -> 30465.181 | K9: =K93/((1-Assumptions!$H$28)*(1-Assumptions!$H$29)) -> 39045.128 | ... O9: =O93/((1-Assumptions!$H$28)*(1-Assumptions!$H$29)) -> 30437.433 | P9: =SUM(D9:O9) -> 333664.44
A10: svc_rev | B10: Maintenance and repair revenue | D10: =Drivers!D8*Assumptions!$H$14 -> 47493.619 | E10: =Drivers!E8*Assumptions!$H$14 -> 27826.365 | F10: =Drivers!F8*Assumptions!$H$14 -> 22788.956 | G10: =Drivers!G8*Assumptions!$H$14 -> 36907.954 | H10: =Drivers!H8*Assumptions!$H$14 -> 43967.133 | I10: =Drivers!I8*Assumptions!$H$14 -> 62422.863 | J10: =Drivers!J8*Assumptions!$H$14 -> 83178.978 | K10: =Drivers!K8*Assumptions!$H$14 -> 89350.198 | ... O10: =Drivers!O8*Assumptions!$H$14 -> 59638.215 | P10: =SUM(D10:O10) -> 706198.95
A11: gross_rev | B11: Gross revenue | D11: =D8+D9+D10 -> 206352.9 | E11: =E8+E9+E10 -> 140395.3 | F11: =F8+F9+F10 -> 123012.47 | G11: =G8+G9+G10 -> 115910.76 | H11: =H8+H9+H10 -> 116365.57 | I11: =I8+I9+I10 -> 216196.43 | J11: =J8+J9+J10 -> 411213.35 | K11: =K8+K9+K10 -> 483916.28 | ... O11: =O8+O9+O10 -> 289519.52 | P11: =SUM(D11:O11) -> 3418772
A12: discounts | B12: Sales discounts & promotional allowances | D12: =-(D8*D91+D9*Assumptions!$H$28) -> -3646.0961 | E12: =-(E8*E91+E9*Assumptions!$H$28) -> -2592.8166 | F12: =-(F8*F91+F9*Assumptions!$H$28) -> -2298.0862 | G12: =-(G8*G91+G9*Assumptions!$H$28) -> -1804.191 | H12: =-(H8*H91+H9*Assumptions!$H$28) -> -1659.835 | I12: =-(I8*I91+I9*Assumptions!$H$28) -> -3533.0093 | J12: =-(J8*J91+J9*Assumptions!$H$28) -> -7571.3255 | K12: =-(K8*K91+K9*Assumptions!$H$28) -> -9101.6342 | ... O12: =-(O8*O91+O9*Assumptions!$H$28) -> -5285.7954 | P12: =SUM(D12:O12) -> -62428.079
A13: returns | B13: Sales returns & refunds | D13: =-(Assumptions!$H$27*D8*(1-D91)+Assumptions!$H$29*D9*(1-Assumptions!$H$28)) -> -4815.4251 | E13: =-(Assumptions!$H$27*E8*(1-E91)+Assumptions!$H$29*E9*(1-Assumptions!$H$28)) -> -3394.9598 | F13: =-(Assumptions!$H$27*F8*(1-F91)+Assumptions!$H$29*F9*(1-Assumptions!$H$28)) -> -3042.2106 | G13: =-(Assumptions!$H$27*G8*(1-G91)+Assumptions!$H$29*G9*(1-Assumptions!$H$28)) -> -2411.8668 | H13: =-(Assumptions!$H$27*H8*(1-H91)+Assumptions!$H$29*H9*(1-Assumptions!$H$28)) -> -2198.0405 | I13: =-(Assumptions!$H$27*I8*(1-I91)+Assumptions!$H$29*I9*(1-Assumptions!$H$28)) -> -4654.3994 | J13: =-(Assumptions!$H$27*J8*(1-J91)+Assumptions!$H$29*J9*(1-Assumptions!$H$28)) -> -9863.6222 | K13: =-(Assumptions!$H$27*K8*(1-K91)+Assumptions!$H$29*K9*(1-Assumptions!$H$28)) -> -11874.159 | ... O13: =-(Assumptions!$H$27*O8*(1-O91)+Assumptions!$H$29*O9*(1-Assumptions!$H$28)) -> -6950.1327 | P13: =SUM(D13:O13) -> -81904.555
A14: returns_allow | B14: Sales returns and allowances | D14: =D12+D13 -> -8461.5212 | E14: =E12+E13 -> -5987.7763 | F14: =F12+F13 -> -5340.2968 | G14: =G12+G13 -> -4216.0578 | H14: =H12+H13 -> -3857.8755 | I14: =I12+I13 -> -8187.4088 | J14: =J12+J13 -> -17434.948 | K14: =K12+K13 -> -20975.793 | ... O14: =O12+O13 -> -12235.928 | P14: =SUM(D14:O14) -> -144332.63
A15: net_rev | B15: Net revenue | D15: =D11+D14 -> 197891.38 | E15: =E11+E14 -> 134407.52 | F15: =F11+F14 -> 117672.18 | G15: =G11+G14 -> 111694.7 | H15: =H11+H14 -> 112507.7 | I15: =I11+I14 -> 208009.03 | J15: =J11+J14 -> 393778.4 | K15: =K11+K14 -> 462940.49 | ... O15: =O11+O14 -> 277283.59 | P15: =SUM(D15:O15) -> 3274439.3
A16: cogs_bike | B16: Cost of goods sold - e-bikes | D16: =-(D89*Assumptions!$H$30*(1+Assumptions!$H$13)-Assumptions!$H$12*D92) -> -91954.553 | E16: =-(E89*Assumptions!$H$30*(1+Assumptions!$H$13)-Assumptions!$H$12*E92) -> -67990.118 | F16: =-(F89*Assumptions!$H$30*(1+Assumptions!$H$13)-Assumptions!$H$12*F92) -> -57328.802 | G16: =-(G89*Assumptions!$H$30*(1+Assumptions!$H$13)-Assumptions!$H$12*G92) -> -42931.842 | H16: =-(H89*Assumptions!$H$30*(1+Assumptions!$H$13)-Assumptions!$H$12*H92) -> -41340.638 | I16: =-(I89*Assumptions!$H$30*(1+Assumptions!$H$13)-Assumptions!$H$12*I92) -> -90134.657 | J16: =-(J89*Assumptions!$H$30*(1+Assumptions!$H$13)-Assumptions!$H$12*J92) -> -202965.68 | K16: =-(K89*Assumptions!$H$30*(1+Assumptions!$H$13)-Assumptions!$H$12*K92) -> -242493.36 | ... O16: =-(O89*Assumptions!$H$30*(1+Assumptions!$H$13)-Assumptions!$H$12*O92) -> -136036.47 | P16: =SUM(D16:O16) -> -1622603.4
A17: cogs_acc | B17: Cost of goods sold - accessories, batteries & parts | D17: =-(Drivers!D7*Assumptions!$H$8*Assumptions!$H$31*(1+Assumptions!$H$13)-Assumptions!$H$12*D93) -> -13229.13 | E17: =-(Drivers!E7*Assumptions!$H$8*Assumptions!$H$31*(1+Assumptions!$H$13)-Assumptions!$H$12*E93) -> -7091.1138 | F17: =-(Drivers!F7*Assumptions!$H$8*Assumptions!$H$31*(1+Assumptions!$H$13)-Assumptions!$H$12*F93) -> -8898.6368 | G17: =-(Drivers!G7*Assumptions!$H$8*Assumptions!$H$31*(1+Assumptions!$H$13)-Assumptions!$H$12*G93) -> -8836.3304 | H17: =-(Drivers!H7*Assumptions!$H$8*Assumptions!$H$31*(1+Assumptions!$H$13)-Assumptions!$H$12*H93) -> -6486.1498 | I17: =-(Drivers!I7*Assumptions!$H$8*Assumptions!$H$31*(1+Assumptions!$H$13)-Assumptions!$H$12*I93) -> -11898.992 | J17: =-(Drivers!J7*Assumptions!$H$8*Assumptions!$H$31*(1+Assumptions!$H$13)-Assumptions!$H$12*J93) -> -16761.984 | K17: =-(Drivers!K7*Assumptions!$H$8*Assumptions!$H$31*(1+Assumptions!$H$13)-Assumptions!$H$12*K93) -> -21482.682 | ... O17: =-(Drivers!O7*Assumptions!$H$8*Assumptions!$H$31*(1+Assumptions!$H$13)-Assumptions!$H$12*O93) -> -16746.717 | P17: =SUM(D17:O17) -> -183582.62
A18: shrink | B18: Inventory shrinkage & write-offs | D18: =D94*Assumptions!$H$32 -> -423.31079 | E18: =E94*Assumptions!$H$32 -> -302.16374 | F18: =F94*Assumptions!$H$32 -> -266.53173 | G18: =G94*Assumptions!$H$32 -> -208.34055 | H18: =H94*Assumptions!$H$32 -> -192.47848 | I18: =I94*Assumptions!$H$32 -> -410.6335 | J18: =J94*Assumptions!$H$32 -> -884.292 | K18: =K94*Assumptions!$H$32 -> -1062.3692 | ... O18: =O94*Assumptions!$H$32 -> -614.87455 | P18: =SUM(D18:O18) -> -7268.9795
A19: svc_parts | B19: Service parts cost | D19: =-D10*Assumptions!$H$33 -> -10430.573 | E19: =-E10*Assumptions!$H$33 -> -6111.2409 | F19: =-F10*Assumptions!$H$33 -> -5004.9225 | G19: =-G10*Assumptions!$H$33 -> -8105.7441 | H19: =-H10*Assumptions!$H$33 -> -9656.0846 | I19: =-I10*Assumptions!$H$33 -> -13709.342 | J19: =-J10*Assumptions!$H$33 -> -18267.811 | K19: =-K10*Assumptions!$H$33 -> -19623.137 | ... O19: =-O10*Assumptions!$H$33 -> -13097.776 | P19: =SUM(D19:O19) -> -155095.78
A20: svc_labour | B20: Direct service labour | D20: =-MIN(Drivers!D10,D10*Assumptions!$H$34) -> -8051.9769 | E20: =-MIN(Drivers!E10,E10*Assumptions!$H$34) -> -4717.6285 | F20: =-MIN(Drivers!F10,F10*Assumptions!$H$34) -> -3863.5958 | G20: =-MIN(Drivers!G10,G10*Assumptions!$H$34) -> -6257.3035 | H20: =-MIN(Drivers!H10,H10*Assumptions!$H$34) -> -7454.1031 | I20: =-MIN(Drivers!I10,I10*Assumptions!$H$34) -> -10583.052 | J20: =-MIN(Drivers!J10,J10*Assumptions!$H$34) -> -14102.004 | K20: =-MIN(Drivers!K10,K10*Assumptions!$H$34) -> -15148.261 | ... O20: =-MIN(Drivers!O10,O10*Assumptions!$H$34) -> -10110.948 | P20: =SUM(D20:O20) -> -119727.61
A21: cogs | B21: Cost of goods sold (total cost of sales) | D21: =D94+D18+D19+D20 -> -124089.54 | E21: =E94+E18+E19+E20 -> -86212.265 | F21: =F94+F18+F19+F20 -> -75362.489 | G21: =G94+G18+G19+G20 -> -66339.561 | H21: =H94+H18+H19+H20 -> -65129.454 | I21: =I94+I18+I19+I20 -> -126736.68 | J21: =J94+J18+J19+J20 -> -252981.77 | K21: =K94+K18+K19+K20 -> -299809.8 | ... O21: =O94+O18+O19+O20 -> -176606.78 | P21: =SUM(D21:O21) -> -2088278.4
A22: gross_profit | B22: Gross profit | D22: =D15+D21 -> 73801.833 | E22: =E15+E21 -> 48195.258 | F22: =F15+F21 -> 42309.688 | G22: =G15+G21 -> 45355.141 | H22: =H15+H21 -> 47378.243 | I22: =I15+I21 -> 81272.35 | J22: =J15+J21 -> 140796.63 | K22: =K15+K21 -> 163130.68 | ... O22: =O15+O21 -> 100676.81 | P22: =SUM(D22:O22) -> 1186160.9
A23: emp_comp | B23: Employee compensation | D23: =-(Drivers!D9+D95+Drivers!D10+D20) -> -32839.367 | E23: =-(Drivers!E9+E95+Drivers!E10+E20) -> -33279.868 | F23: =-(Drivers!F9+F95+Drivers!F10+F20) -> -33911.86 | G23: =-(Drivers!G9+G95+Drivers!G10+G20) -> -33613.054 | H23: =-(Drivers!H9+H95+Drivers!H10+H20) -> -28790.992 | I23: =-(Drivers!I9+I95+Drivers!I10+I20) -> -30270.393 | J23: =-(Drivers!J9+J95+Drivers!J10+J20) -> -45929.283 | K23: =-(Drivers!K9+K95+Drivers!K10+K20) -> -45706.259 | ... O23: =-(Drivers!O9+O95+Drivers!O10+O20) -> -48526.421 | P23: =SUM(D23:O23) -> -480121.89
A24: rent | B24: Rent and occupancy | D24: =-Drivers!D11 -> -20157.1 | E24: =-Drivers!E11 -> -20157.1 | F24: =-Drivers!F11 -> -20157.1 | G24: =-Drivers!G11 -> -20761.813 | H24: =-Drivers!H11 -> -20761.813 | I24: =-Drivers!I11 -> -20761.813 | J24: =-Drivers!J11 -> -20761.813 | K24: =-Drivers!K11 -> -20761.813 | ... O24: =-Drivers!O11 -> -20761.813 | P24: =SUM(D24:O24) -> -247327.62
A25: utilities | B25: Utilities | D25: =-Drivers!D12 -> -1546.8788 | E25: =-Drivers!E12 -> -1857.054 | F25: =-Drivers!F12 -> -2290.4138 | G25: =-Drivers!G12 -> -2197.1695 | H25: =-Drivers!H12 -> -2085.834 | I25: =-Drivers!I12 -> -1961.932 | J25: =-Drivers!J12 -> -1760.9398 | K25: =-Drivers!K12 -> -1216.7877 | ... O25: =-Drivers!O12 -> -1240.168 | P25: =SUM(D25:O25) -> -19734.181
A26: marketing | B26: Marketing and advertising | D26: =-Drivers!D13 -> -5903.9668 | E26: =-Drivers!E13 -> -5074.008 | F26: =-Drivers!F13 -> -5157.6738 | G26: =-Drivers!G13 -> -5029.859 | H26: =-Drivers!H13 -> -5430.009 | I26: =-Drivers!I13 -> -6559.4602 | J26: =-Drivers!J13 -> -8211.979 | K26: =-Drivers!K13 -> -10437.502 | ... O26: =-Drivers!O13 -> -8066.0382 | P26: =SUM(D26:O26) -> -87485.542
A27: admin | B27: Administrative expenses (incl. insurance & corporate allocation) | D27: =-(Drivers!D14+Drivers!D16+Assumptions!$H$59) -> -6359.0252 | E27: =-(Drivers!E14+Drivers!E16+Assumptions!$H$59) -> -6359.0252 | F27: =-(Drivers!F14+Drivers!F16+Assumptions!$H$59) -> -6359.0252 | G27: =-(Drivers!G14+Drivers!G16+Assumptions!$H$59) -> -6458.5324 | H27: =-(Drivers!H14+Drivers!H16+Assumptions!$H$59) -> -6458.5324 | I27: =-(Drivers!I14+Drivers!I16+Assumptions!$H$59) -> -6458.5324 | J27: =-(Drivers!J14+Drivers!J16+Assumptions!$H$59) -> -6458.5324 | K27: =-(Drivers!K14+Drivers!K16+Assumptions!$H$59) -> -6458.5324 | ... O27: =-(Drivers!O14+Drivers!O16+Assumptions!$H$59) -> -6458.5324 | P27: =SUM(D27:O27) -> -77203.868
A28: freight | B28: Freight and logistics | D28: =-Assumptions!$H$36*D99 -> -4640.5707 | E28: =-Assumptions!$H$36*E99 -> -3730.7239 | F28: =-Assumptions!$H$36*F99 -> -5410.5445 | G28: =-Assumptions!$H$36*G99 -> -3507.9876 | H28: =-Assumptions!$H$36*H99 -> -2526.9975 | I28: =-Assumptions!$H$36*I99 -> -6565.209 | J28: =-Assumptions!$H$36*J99 -> -5414.0229 | K28: =-Assumptions!$H$36*K99 -> -4766.4335 | ... O28: =-Assumptions!$H$36*O99 -> -6424.0396 | P28: =SUM(D28:O28) -> -69539.28
A29: fees | B29: Merchant and financing fees | D29: =-Assumptions!$H$37*D15 -> -3945.3592 | E29: =-Assumptions!$H$37*E15 -> -2679.682 | F29: =-Assumptions!$H$37*F15 -> -2346.0295 | G29: =-Assumptions!$H$37*G15 -> -2226.8566 | H29: =-Assumptions!$H$37*H15 -> -2243.0653 | I29: =-Assumptions!$H$37*I15 -> -4147.0747 | J29: =-Assumptions!$H$37*J15 -> -7850.7577 | K29: =-Assumptions!$H$37*K15 -> -9229.6417 | ... O29: =-Assumptions!$H$37*O15 -> -5528.2013 | P29: =SUM(D29:O29) -> -65282.477
A30: storage | B30: Inventory storage, handling & obsolescence | D30: =-Assumptions!$H$38/12*(C43+D43)/2 -> -3508.8808 | E30: =-Assumptions!$H$38/12*(D43+E43)/2 -> -3706.7959 | F30: =-Assumptions!$H$38/12*(E43+F43)/2 -> -4201.7156 | G30: =-Assumptions!$H$38/12*(F43+G43)/2 -> -4784.3254 | H30: =-Assumptions!$H$38/12*(G43+H43)/2 -> -5079.4191 | I30: =-Assumptions!$H$38/12*(H43+I43)/2 -> -5524.9442 | J30: =-Assumptions!$H$38/12*(I43+J43)/2 -> -5487.8539 | K30: =-Assumptions!$H$38/12*(J43+K43)/2 -> -4400.8153 | ... O30: =-Assumptions!$H$38/12*(N43+O43)/2 -> -3534.4142 | P30: =SUM(D30:O30) -> -50109.521
A31: opex | B31: Total operating expenses (before D&A) | D31: =D23+D24+D25+D26+D27+D28+D29+D30 -> -78901.149 | E31: =E23+E24+E25+E26+E27+E28+E29+E30 -> -76844.257 | F31: =F23+F24+F25+F26+F27+F28+F29+F30 -> -79834.362 | G31: =G23+G24+G25+G26+G27+G28+G29+G30 -> -78579.598 | H31: =H23+H24+H25+H26+H27+H28+H29+H30 -> -73376.663 | I31: =I23+I24+I25+I26+I27+I28+I29+I30 -> -82249.358 | J31: =J23+J24+J25+J26+J27+J28+J29+J30 -> -101875.18 | K31: =K23+K24+K25+K26+K27+K28+K29+K30 -> -102977.78 | ... O31: =O23+O24+O25+O26+O27+O28+O29+O30 -> -100539.63 | P31: =SUM(D31:O31) -> -1096804.4
A32: ebitda | B32: EBITDA | D32: =D22+D31 -> -5099.3153 | E32: =E22+E31 -> -28648.999 | F32: =F22+F31 -> -37524.674 | G32: =G22+G31 -> -33224.457 | H32: =H22+H31 -> -25998.42 | I32: =I22+I31 -> -977.00844 | J32: =J22+J31 -> 38921.453 | K32: =K22+K31 -> 60152.899 | ... O32: =O22+O31 -> 137.18539 | P32: =SUM(D32:O32) -> 89356.522
A33: da | B33: Depreciation and amortization | D33: =-(Drivers!D18+C121/Assumptions!$H$58) -> -3712.19 | E33: =-(Drivers!E18+D121/Assumptions!$H$58) -> -3101.04 | F33: =-(Drivers!F18+E121/Assumptions!$H$58) -> -3101.04 | G33: =-(Drivers!G18+F121/Assumptions!$H$58) -> -3101.04 | H33: =-(Drivers!H18+G121/Assumptions!$H$58) -> -3201.04 | I33: =-(Drivers!I18+H121/Assumptions!$H$58) -> -3201.04 | J33: =-(Drivers!J18+I121/Assumptions!$H$58) -> -3401.04 | K33: =-(Drivers!K18+J121/Assumptions!$H$58) -> -3401.04 | ... O33: =-(Drivers!O18+N121/Assumptions!$H$58) -> -3401.04 | P33: =SUM(D33:O33) -> -39823.63
A34: ebit | B34: EBIT (operating profit) | D34: =D32+D33 -> -8811.5053 | E34: =E32+E33 -> -31750.039 | F34: =F32+F33 -> -40625.714 | G34: =G32+G33 -> -36325.497 | H34: =H32+H33 -> -29199.46 | I34: =I32+I33 -> -4178.0484 | J34: =J32+J33 -> 35520.413 | K34: =K32+K33 -> 56751.859 | ... O34: =O32+O33 -> -3263.8546 | P34: =SUM(D34:O34) -> 49532.892
A35: interest | B35: Interest expense | D35: =-(C113*(Assumptions!$H$47+Assumptions!$H$16+Assumptions!$H$48)+C56*(Assumptions!$H$47+Assumptions!$H$16+Assumptions!$H$49))/12 -> -628.12439 | E35: =-(D113*(Assumptions!$H$47+Assumptions!$H$16+Assumptions!$H$48)+D56*(Assumptions!$H$47+Assumptions!$H$16+Assumptions!$H$49))/12 -> -604.86048 | F35: =-(E113*(Assumptions!$H$47+Assumptions!$H$16+Assumptions!$H$48)+E56*(Assumptions!$H$47+Assumptions!$H$16+Assumptions!$H$49))/12 -> -581.59657 | G35: =-(F113*(Assumptions!$H$47+Assumptions!$H$16+Assumptions!$H$48)+F56*(Assumptions!$H$47+Assumptions!$H$16+Assumptions!$H$49))/12 -> -558.33266 | H35: =-(G113*(Assumptions!$H$47+Assumptions!$H$16+Assumptions!$H$48)+G56*(Assumptions!$H$47+Assumptions!$H$16+Assumptions!$H$49))/12 -> -1130.0271 | I35: =-(H113*(Assumptions!$H$47+Assumptions!$H$16+Assumptions!$H$48)+H56*(Assumptions!$H$47+Assumptions!$H$16+Assumptions!$H$49))/12 -> -1406.5132 | J35: =-(I113*(Assumptions!$H$47+Assumptions!$H$16+Assumptions!$H$48)+I56*(Assumptions!$H$47+Assumptions!$H$16+Assumptions!$H$49))/12 -> -1383.2493 | K35: =-(J113*(Assumptions!$H$47+Assumptions!$H$16+Assumptions!$H$48)+J56*(Assumptions!$H$47+Assumptions!$H$16+Assumptions!$H$49))/12 -> -928.52703 | ... O35: =-(N113*(Assumptions!$H$47+Assumptions!$H$16+Assumptions!$H$48)+N56*(Assumptions!$H$47+Assumptions!$H$16+Assumptions!$H$49))/12 -> -372.2214 | P35: =SUM(D35:O35) -> -8849.6997
A36: pbt | B36: Profit before tax | D36: =D34+D35 -> -9439.6297 | E36: =E34+E35 -> -32354.899 | F36: =F34+F35 -> -41207.311 | G36: =G34+G35 -> -36883.829 | H36: =H34+H35 -> -30329.487 | I36: =I34+I35 -> -5584.5616 | J36: =J34+J35 -> 34137.164 | K36: =K34+K35 -> 55823.332 | ... O36: =O34+O35 -> -3636.076 | P36: =SUM(D36:O36) -> 40683.193
A37: tax | B37: Income taxes | D37: =-(D118-IF(Drivers!D20,0,C118)) -> 0 | E37: =-(E118-IF(Drivers!E20,0,D118)) -> 0 | F37: =-(F118-IF(Drivers!F20,0,E118)) -> 0 | G37: =-(G118-IF(Drivers!G20,0,F118)) -> 0 | H37: =-(H118-IF(Drivers!H20,0,G118)) -> 0 | I37: =-(I118-IF(Drivers!I20,0,H118)) -> 0 | J37: =-(J118-IF(Drivers!J20,0,I118)) -> 0 | K37: =-(K118-IF(Drivers!K20,0,J118)) -> 0 | ... O37: =-(O118-IF(Drivers!O20,0,N118)) -> 836.29748 | P37: =SUM(D37:O37) -> -6806.7563
A38: net_income | B38: Net income | D38: =D36+D37 -> -9439.6297 | E38: =E36+E37 -> -32354.899 | F38: =F36+F37 -> -41207.311 | G38: =G36+G37 -> -36883.829 | H38: =H36+H37 -> -30329.487 | I38: =I36+I37 -> -5584.5616 | J38: =J36+J37 -> 34137.164 | K38: =K36+K37 -> 55823.332 | ... O38: =O36+O37 -> -2799.7785 | P38: =SUM(D38:O38) -> 33876.436
A40: BALANCE SHEET (forecast; column C = actual 30-Sep-2026 from the general ledger)
A41: cash | B41: Cash and cash equivalents | C41: =Hist_Balances!$AJ$6 -> 354459.44 | D41: =C41+D82 -> 272095.28 | E41: =D41+E82 -> 201231.49 | F41: =E41+F82 -> 116355.99 | G41: =F41+G82 -> 100635.64 | H41: =G41+H82 -> 100431.92 | I41: =H41+I82 -> 90243.946 | J41: =I41+J82 -> 100222.88 | K41: =J41+K82 -> 194462.24 | ... O41: =N41+O82 -> 341845.25
A42: ar | B42: Accounts receivable | C42: =Hist_Balances!$AJ$7+Hist_Balances!$AJ$8+Hist_Balances!$AJ$9+Hist_Balances!$AJ$10 -> 22724.22 | D42: =Assumptions!$H$39*D15*(1+Assumptions!$H$45) -> 16328.909 | E42: =Assumptions!$H$39*E15*(1+Assumptions!$H$45) -> 11090.57 | F42: =Assumptions!$H$39*F15*(1+Assumptions!$H$45) -> 9709.6613 | G42: =Assumptions!$H$39*G15*(1+Assumptions!$H$45) -> 9216.4329 | H42: =Assumptions!$H$39*H15*(1+Assumptions!$H$45) -> 9283.5167 | I42: =Assumptions!$H$39*I15*(1+Assumptions!$H$45) -> 17163.762 | J42: =Assumptions!$H$39*J15*(1+Assumptions!$H$45) -> 32492.43 | K42: =Assumptions!$H$39*K15*(1+Assumptions!$H$45) -> 38199.305 | ... O42: =Assumptions!$H$39*O15*(1+Assumptions!$H$45) -> 22879.918
A43: inventory | B43: Inventory (merchandise at cost) | C43: =Hist_Balances!$AJ$11 -> 342554.88 | D43: =C43+D99+D94+D18 -> 359221.27 | E43: =D43+E99+E94+E18 -> 382137.91 | F43: =E43+F99+F94+F18 -> 458205.2 | G43: =F43+G99+G94+G18 -> 498659.89 | H43: =G43+H99+H94+H18 -> 517223.93 | I43: =H43+I99+I94+I18 -> 587764.91 | J43: =I43+J99+J94+J18 -> 509805.87 | K43: =J43+K99+K94+K18 -> 370357.18 | ... O43: =N43+O99+O94+O18 -> 361375.2
A44: wip | B44: Service work in progress | C44: =Hist_Balances!$AJ$12 -> 8663.8 | D44: =-Assumptions!$H$40*(D19+D20) -> 4138.3702 | E44: =-Assumptions!$H$40*(E19+E20) -> 2424.6584 | F44: =-Assumptions!$H$40*(F19+F20) -> 1985.7223 | G44: =-Assumptions!$H$40*(G19+G20) -> 3215.9852 | H44: =-Assumptions!$H$40*(H19+H20) -> 3831.0888 | I44: =-Assumptions!$H$40*(I19+I20) -> 5439.2342 | J44: =-Assumptions!$H$40*(J19+J20) -> 7247.8243 | K44: =-Assumptions!$H$40*(K19+K20) -> 7785.5553 | ... O44: =-Assumptions!$H$40*(O19+O20) -> 5196.593
A45: prepaid | B45: Prepaid expenses & supplier deposits | C45: =Hist_BS!$AI$10 -> 26792.86 | D45: =D102+D103 -> 24106.184 | E45: =E102+E103 -> 17867.647 | F45: =F102+F103 -> 22305.053 | G45: =G102+G103 -> 42920.792 | H45: =H102+H103 -> 36289.458 | I45: =I102+I103 -> 50349.86 | J45: =J102+J103 -> 43016.89 | K45: =K102+K103 -> 37760.006 | ... O45: =O102+O103 -> 34244.764
A46: gst_rec | B46: Sales tax recoverable | C46: =Hist_BS!$AI$11 -> 0 | D46: =MAX(0,-D104) -> 0 | E46: =MAX(0,-E104) -> 0 | F46: =MAX(0,-F104) -> 2593.7451 | G46: =MAX(0,-G104) -> 1717.2372 | H46: =MAX(0,-H104) -> 1859.0929 | I46: =MAX(0,-I104) -> 3623.107 | J46: =MAX(0,-J104) -> 0 | K46: =MAX(0,-K104) -> 0 | ... O46: =MAX(0,-O104) -> 0
A47: current_assets | B47: Total current assets | C47: =Hist_BS!$AI$12 -> 755195.2 | D47: =D41+D42+D43+D44+D45+D46 -> 675890.02 | E47: =E41+E42+E43+E44+E45+E46 -> 614752.28 | F47: =F41+F42+F43+F44+F45+F46 -> 611155.38 | G47: =G41+G42+G43+G44+G45+G46 -> 656365.98 | H47: =H41+H42+H43+H44+H45+H46 -> 668919.01 | I47: =I41+I42+I43+I44+I45+I46 -> 754584.82 | J47: =J41+J42+J43+J44+J45+J46 -> 692785.89 | K47: =K41+K42+K43+K44+K45+K46 -> 648564.28 | ... O47: =O41+O42+O43+O44+O45+O46 -> 765541.73
A48: ppe_gross | B48: Property, plant and equipment (cost) | C48: =Hist_Balances!$AJ$16+Hist_Balances!$AJ$17+Hist_Balances!$AJ$18 -> 281000 | D48: =C48+Drivers!D17 -> 281000 | E48: =D48+Drivers!E17 -> 281000 | F48: =E48+Drivers!F17 -> 281000 | G48: =F48+Drivers!G17 -> 287000 | H48: =G48+Drivers!H17 -> 287000 | I48: =H48+Drivers!I17 -> 299000 | J48: =I48+Drivers!J17 -> 299000 | K48: =J48+Drivers!K17 -> 299000 | ... O48: =N48+Drivers!O17 -> 299000
A49: acc_dep | B49: Accumulated depreciation | C49: =Hist_Balances!$AJ$19 -> -106812.13 | D49: =C49+D33 -> -110524.32 | E49: =D49+E33 -> -113625.36 | F49: =E49+F33 -> -116726.4 | G49: =F49+G33 -> -119827.44 | H49: =G49+H33 -> -123028.48 | I49: =H49+I33 -> -126229.52 | J49: =I49+J33 -> -129630.56 | K49: =J49+K33 -> -133031.6 | ... O49: =N49+O33 -> -146635.76
A50: ppe_net | B50: Net property, plant and equipment | C50: =Hist_BS!$AI$15 -> 174187.87 | D50: =D48+D49 -> 170475.68 | E50: =E48+E49 -> 167374.64 | F50: =F48+F49 -> 164273.6 | G50: =G48+G49 -> 167172.56 | H50: =H48+H49 -> 163971.52 | I50: =I48+I49 -> 172770.48 | J50: =J48+J49 -> 169369.44 | K50: =K48+K49 -> 165968.4 | ... O50: =O48+O49 -> 152364.24
A51: total_assets | B51: TOTAL ASSETS | C51: =Hist_BS!$AI$16 -> 929383.07 | D51: =D47+D50 -> 846365.7 | E51: =E47+E50 -> 782126.92 | F51: =F47+F50 -> 775428.98 | G51: =G47+G50 -> 823538.54 | H51: =H47+H50 -> 832890.53 | I51: =I47+I50 -> 927355.3 | J51: =J47+J50 -> 862155.33 | K51: =K47+K50 -> 814532.68 | ... O51: =O47+O50 -> 917905.97
A52: ap | B52: Accounts payable | C52: =Hist_BS!$AI$17 -> 185924.9 | D52: =D106+D107 -> 136154.6 | E52: =E106+E107 -> 109621.85 | F52: =F106+F107 -> 148681.81 | G52: =G106+G107 -> 107094.42 | H52: =H106+H107 -> 86105.195 | I52: =I106+I107 -> 187367.03 | J52: =J106+J107 -> 169507.66 | K52: =K106+K107 -> 157520.58 | ... O52: =O106+O107 -> 183663.88
A53: accrued | B53: Accrued expenses (payroll & head office) | C53: =Hist_BS!$AI$18 -> 30310.02 | D53: =D108+D109 -> 21095.672 | E53: =E108+E109 -> 20298.748 | F53: =F108+F109 -> 20837.728 | G53: =G108+G109 -> 20585.179 | H53: =H108+H109 -> 19422.548 | I53: =I108+I109 -> 22376.722 | J53: =J108+J109 -> 30665.643 | K53: =K108+K109 -> 31727.26 | ... O53: =O108+O109 -> 31268.684
A54: tax_payable | B54: Income taxes payable | C54: =-Hist_Balances!$AJ$24 -> 0 | D54: =C54-D37-D120 -> 0 | E54: =D54-E37-E120 -> 0 | F54: =E54-F37-F120 -> 0 | G54: =F54-G37-G120 -> 0 | H54: =G54-H37-H120 -> 0 | I54: =H54-I37-I120 -> 0 | J54: =I54-J37-J120 -> 0 | K54: =J54-K37-K120 -> 0 | ... O54: =N54-O37-O120 -> 6806.7563
A55: gst_pay | B55: Sales tax payable | C55: =Hist_BS!$AI$20 -> 11736.86 | D55: =MAX(0,D104) -> 1310.4338 | E55: =MAX(0,E104) -> 922.89483 | F55: =MAX(0,F104) -> 0 | G55: =MAX(0,G104) -> 0 | H55: =MAX(0,H104) -> 0 | I55: =MAX(0,I104) -> 0 | J55: =MAX(0,J104) -> 9399.9864 | K55: =MAX(0,K104) -> 23046.133 | ... O55: =MAX(0,O104) -> 10878.96
A56: revolver | B56: Short-term borrowings - revolving line of credit | C56: =-Hist_Balances!$AJ$26 -> 0 | D56: =C56+D77+D78 -> 0 | E56: =D56+E77+E78 -> 0 | F56: =E56+F77+F78 -> 0 | G56: =F56+G77+G78 -> 131000 | H56: =G56+H77+H78 -> 197000 | I56: =H56+I77+I78 -> 197000 | J56: =I56+J77+J78 -> 102000 | K56: =J56+K77+K78 -> 0 | ... O56: =N56+O77+O78 -> 0
A57: term_current | B57: Current portion of long-term debt | C57: =Hist_BS!$AI$22 -> 50000.04 | D57: =MIN(D113,12*Assumptions!$H$57) -> 50000.04 | E57: =MIN(E113,12*Assumptions!$H$57) -> 50000.04 | F57: =MIN(F113,12*Assumptions!$H$57) -> 50000.04 | G57: =MIN(G113,12*Assumptions!$H$57) -> 50000.04 | H57: =MIN(H113,12*Assumptions!$H$57) -> 50000.04 | I57: =MIN(I113,12*Assumptions!$H$57) -> 50000.04 | J57: =MIN(J113,12*Assumptions!$H$57) -> 50000.04 | K57: =MIN(K113,12*Assumptions!$H$57) -> 50000.04 | ... O57: =MIN(O113,12*Assumptions!$H$57) -> 50000.04
A58: current_liabilities | B58: Total current liabilities | C58: =Hist_BS!$AI$23 -> 277971.82 | D58: =D52+D53+D54+D55+D56+D57 -> 208560.75 | E58: =E52+E53+E54+E55+E56+E57 -> 180843.54 | F58: =F52+F53+F54+F55+F56+F57 -> 219519.58 | G58: =G52+G53+G54+G55+G56+G57 -> 308679.64 | H58: =H52+H53+H54+H55+H56+H57 -> 352527.78 | I58: =I52+I53+I54+I55+I56+I57 -> 456743.79 | J58: =J52+J53+J54+J55+J56+J57 -> 361573.33 | K58: =K52+K53+K54+K55+K56+K57 -> 262294.02 | ... O58: =O52+O53+O54+O55+O56+O57 -> 282618.32
A59: term_lt | B59: Long-term debt (non-current portion) | C59: =Hist_BS!$AI$24 -> 62499.85 | D59: =D113-D57 -> 58333.18 | E59: =E113-E57 -> 54166.51 | F59: =F113-F57 -> 49999.84 | G59: =G113-G57 -> 45833.17 | H59: =H113-H57 -> 41666.5 | I59: =I113-I57 -> 37499.83 | J59: =J113-J57 -> 33333.16 | K59: =K113-K57 -> 29166.49 | ... O59: =O113-O57 -> 12499.81
A60: total_liabilities | B60: TOTAL LIABILITIES | C60: =Hist_BS!$AI$25 -> 340471.67 | D60: =D58+D59 -> 266893.93 | E60: =E58+E59 -> 235010.05 | F60: =F58+F59 -> 269519.42 | G60: =G58+G59 -> 354512.81 | H60: =H58+H59 -> 394194.28 | I60: =I58+I59 -> 494243.62 | J60: =J58+J59 -> 394906.49 | K60: =K58+K59 -> 291460.51 | ... O60: =O58+O59 -> 295118.13
A61: equity_cap | B61: Share capital / allocated corporate equity | C61: =-Hist_Balances!$AJ$28 -> 600000 | D61: =C61+D79 -> 600000 | E61: =D61+E79 -> 600000 | F61: =E61+F79 -> 600000 | G61: =F61+G79 -> 600000 | H61: =G61+H79 -> 600000 | I61: =H61+I79 -> 600000 | J61: =I61+J79 -> 600000 | K61: =J61+K79 -> 600000 | ... O61: =N61+O79 -> 600000
A62: retained | B62: Retained earnings | C62: =-(Hist_Balances!$AJ$29+Hist_Balances!$AJ$30) -> -98211.57 | D62: =C62+IF(Drivers!D22,C63+D38,0)+D80 -> -98211.57 | E62: =D62+IF(Drivers!E22,D63+E38,0)+E80 -> -98211.57 | F62: =E62+IF(Drivers!F22,E63+F38,0)+F80 -> -94090.44 | G62: =F62+IF(Drivers!G22,F63+G38,0)+G80 -> -94090.44 | H62: =G62+IF(Drivers!H22,G63+H38,0)+H80 -> -94090.44 | I62: =H62+IF(Drivers!I22,H63+I38,0)+I80 -> -94090.44 | J62: =I62+IF(Drivers!J22,I63+J38,0)+J80 -> -94090.44 | K62: =J62+IF(Drivers!K22,J63+K38,0)+K80 -> -94090.44 | ... O62: =N62+IF(Drivers!O22,N63+O38,0)+O80 -> -94090.44
A63: cpe | B63: Current period earnings | C63: =Hist_BS!$AI$28 -> 87122.97 | D63: =IF(Drivers!D22,0,C63+D38) -> 77683.34 | E63: =IF(Drivers!E22,0,D63+E38) -> 45328.441 | F63: =IF(Drivers!F22,0,E63+F38) -> 0 | G63: =IF(Drivers!G22,0,F63+G38) -> -36883.829 | H63: =IF(Drivers!H22,0,G63+H38) -> -67213.316 | I63: =IF(Drivers!I22,0,H63+I38) -> -72797.878 | J63: =IF(Drivers!J22,0,I63+J38) -> -38660.714 | K63: =IF(Drivers!K22,0,J63+K38) -> 17162.619 | ... O63: =IF(Drivers!O22,0,N63+O38) -> 116878.28
A64: total_equity | B64: TOTAL EQUITY | C64: =Hist_BS!$AI$29 -> 588911.4 | D64: =D61+D62+D63 -> 579471.77 | E64: =E61+E62+E63 -> 547116.87 | F64: =F61+F62+F63 -> 505909.56 | G64: =G61+G62+G63 -> 469025.73 | H64: =H61+H62+H63 -> 438696.24 | I64: =I61+I62+I63 -> 433111.68 | J64: =J61+J62+J63 -> 467248.85 | K64: =K61+K62+K63 -> 523072.18 | ... O64: =O61+O62+O63 -> 622787.84
A65: total_le | B65: TOTAL LIABILITIES AND EQUITY | C65: =Hist_BS!$AI$30 -> 929383.07 | D65: =D60+D64 -> 846365.7 | E65: =E60+E64 -> 782126.92 | F65: =F60+F64 -> 775428.98 | G65: =G60+G64 -> 823538.54 | H65: =H60+H64 -> 832890.53 | I65: =I60+I64 -> 927355.3 | J65: =J60+J64 -> 862155.33 | K65: =K60+K64 -> 814532.68 | ... O65: =O60+O64 -> 917905.97
A67: CASH FLOW STATEMENT (indirect method)
A68: cf_ni | B68: Net income | D68: =D38 -> -9439.6297 | E68: =E38 -> -32354.899 | F68: =F38 -> -41207.311 | G68: =G38 -> -36883.829 | H68: =H38 -> -30329.487 | I68: =I38 -> -5584.5616 | J68: =J38 -> 34137.164 | K68: =K38 -> 55823.332 | ... O68: =O38 -> -2799.7785 | P68: =SUM(D68:O68) -> 33876.436
A69: cf_da | B69: Depreciation and amortization | D69: =-D33 -> 3712.19 | E69: =-E33 -> 3101.04 | F69: =-F33 -> 3101.04 | G69: =-G33 -> 3101.04 | H69: =-H33 -> 3201.04 | I69: =-I33 -> 3201.04 | J69: =-J33 -> 3401.04 | K69: =-K33 -> 3401.04 | ... O69: =-O33 -> 3401.04 | P69: =SUM(D69:O69) -> 39823.63
A70: d_ar | B70: (Increase) decrease in accounts receivable | D70: =C42-D42 -> 6395.3112 | E70: =D42-E42 -> 5238.3387 | F70: =E42-F42 -> 1380.9088 | G70: =F42-G42 -> 493.22835 | H70: =G42-H42 -> -67.08383 | I70: =H42-I42 -> -7880.2448 | J70: =I42-J42 -> -15328.668 | K70: =J42-K42 -> -5706.8751 | ... O70: =N42-O42 -> 7420.8074 | P70: =SUM(D70:O70) -> -155.69816
A71: d_inv | B71: (Increase) decrease in inventory | D71: =C43-D43 -> -16666.393 | E71: =D43-E43 -> -22916.638 | F71: =E43-F43 -> -76067.29 | G71: =F43-G43 -> -40454.688 | H71: =G43-H43 -> -18564.042 | I71: =H43-I43 -> -70540.98 | J71: =I43-J43 -> 77959.042 | K71: =J43-K43 -> 139448.69 | ... O71: =N43-O43 -> -15867.564 | P71: =SUM(D71:O71) -> -18820.319
A72: d_ap | B72: Increase (decrease) in accounts payable | D72: =D106+D107-C106-C107 -> -49770.299 | E72: =E106+E107-D106-D107 -> -26532.746 | F72: =F106+F107-E106-E107 -> 39059.954 | G72: =G106+G107-F106-F107 -> -41587.388 | H72: =H106+H107-G106-G107 -> -20989.225 | I72: =I106+I107-H106-H107 -> 101261.83 | J72: =J106+J107-I106-I107 -> -17859.367 | K72: =K106+K107-J106-J107 -> -11987.075 | ... O72: =O106+O107-N106-N107 -> -60002.387 | P72: =SUM(D72:O72) -> -2261.02
A73: other_wc | B73: Other working capital adjustments | D73: =C44-D44+C102+C103-D102-D103+D108+D109-C108-C109+D104-C104+D54-C54 -> -12428.668 | E73: =D44-E44+D102+D103-E102-E103+E108+E109-D108-D109+E104-D104+E54-D54 -> 6767.7859 | F73: =E44-F44+E102+E103-F102-F103+F108+F109-E108-E109+F104-E104+F54-E54 -> -6976.1303 | G73: =F44-G44+F102+F103-G102-G103+G108+G109-F108-F109+G104-F104+G54-F54 -> -21222.043 | H73: =G44-H44+G102+G103-H102-H103+H108+H109-G108-G109+H104-G104+H54-G54 -> 4711.7433 | I73: =H44-I44+H102+H103-I102-I103+I108+I109-H108-H109+I104-H104+I54-H54 -> -14478.386 | J73: =I44-J44+I102+I103-J102-J103+J108+J109-I108-I109+J104-I104+J54-I54 -> 26836.394 | K73: =J44-K44+J102+J103-K102-K103+K108+K109-J108-J109+K104-J104+K54-J54 -> 19426.917 | ... O73: =N44-O44+N102+N103-O102-O103+O108+O109-N108-N109+O104-N104+O54-N54 -> 13968.11 | P73: =SUM(D73:O73) -> 2922.8236
A74: cfo | B74: Net cash from operating activities | D74: =D68+D69+D70+D71+D72+D73 -> -78197.489 | E74: =E68+E69+E70+E71+E72+E73 -> -66697.118 | F74: =F68+F69+F70+F71+F72+F73 -> -80708.829 | G74: =G68+G69+G70+G71+G72+G73 -> -136553.68 | H74: =H68+H69+H70+H71+H72+H73 -> -62037.055 | I74: =I68+I69+I70+I71+I72+I73 -> 5978.6966 | J74: =J68+J69+J70+J71+J72+J73 -> 109145.6 | K74: =K68+K69+K70+K71+K72+K73 -> 200406.03 | ... O74: =O68+O69+O70+O71+O72+O73 -> -53879.773 | P74: =SUM(D74:O74) -> 55385.853
A75: cfi | B75: Net cash used in investing activities (capex) | D75: =-Drivers!D17 -> 0 | E75: =-Drivers!E17 -> 0 | F75: =-Drivers!F17 -> 0 | G75: =-Drivers!G17 -> -6000 | H75: =-Drivers!H17 -> 0 | I75: =-Drivers!I17 -> -12000 | J75: =-Drivers!J17 -> 0 | K75: =-Drivers!K17 -> 0 | ... O75: =-Drivers!O17 -> 0 | P75: =SUM(D75:O75) -> -18000
A76: term_repay | B76: Term loan repayments | D76: =-MIN(Assumptions!$H$57,C113) -> -4166.67 | E76: =-MIN(Assumptions!$H$57,D113) -> -4166.67 | F76: =-MIN(Assumptions!$H$57,E113) -> -4166.67 | G76: =-MIN(Assumptions!$H$57,F113) -> -4166.67 | H76: =-MIN(Assumptions!$H$57,G113) -> -4166.67 | I76: =-MIN(Assumptions!$H$57,H113) -> -4166.67 | J76: =-MIN(Assumptions!$H$57,I113) -> -4166.67 | K76: =-MIN(Assumptions!$H$57,J113) -> -4166.67 | ... O76: =-MIN(Assumptions!$H$57,N113) -> -4166.67 | P76: =SUM(D76:O76) -> -50000.04
A77: rev_draw | B77: New borrowings - revolving line of credit | D77: =IF(D112<Assumptions!$H$51,MIN(Assumptions!$H$50-C56,CEILING(MAX(0,Assumptions!$H$52-D112),Assumptions!$H$54)),0) -> 0 | E77: =IF(E112<Assumptions!$H$51,MIN(Assumptions!$H$50-D56,CEILING(MAX(0,Assumptions!$H$52-E112),Assumptions!$H$54)),0) -> 0 | F77: =IF(F112<Assumptions!$H$51,MIN(Assumptions!$H$50-E56,CEILING(MAX(0,Assumptions!$H$52-F112),Assumptions!$H$54)),0) -> 0 | G77: =IF(G112<Assumptions!$H$51,MIN(Assumptions!$H$50-F56,CEILING(MAX(0,Assumptions!$H$52-G112),Assumptions!$H$54)),0) -> 131000 | H77: =IF(H112<Assumptions!$H$51,MIN(Assumptions!$H$50-G56,CEILING(MAX(0,Assumptions!$H$52-H112),Assumptions!$H$54)),0) -> 66000 | I77: =IF(I112<Assumptions!$H$51,MIN(Assumptions!$H$50-H56,CEILING(MAX(0,Assumptions!$H$52-I112),Assumptions!$H$54)),0) -> 0 | J77: =IF(J112<Assumptions!$H$51,MIN(Assumptions!$H$50-I56,CEILING(MAX(0,Assumptions!$H$52-J112),Assumptions!$H$54)),0) -> 0 | K77: =IF(K112<Assumptions!$H$51,MIN(Assumptions!$H$50-J56,CEILING(MAX(0,Assumptions!$H$52-K112),Assumptions!$H$54)),0) -> 0 | ... O77: =IF(O112<Assumptions!$H$51,MIN(Assumptions!$H$50-N56,CEILING(MAX(0,Assumptions!$H$52-O112),Assumptions!$H$54)),0) -> 0 | P77: =SUM(D77:O77) -> 197000
A78: rev_repay | B78: Repayments - revolving line of credit | D78: =IF((D112>Assumptions!$H$53)*(C56>0),-MIN(C56,FLOOR(MAX(0,D112-Assumptions!$H$52),Assumptions!$H$54)),0) -> 0 | E78: =IF((E112>Assumptions!$H$53)*(D56>0),-MIN(D56,FLOOR(MAX(0,E112-Assumptions!$H$52),Assumptions!$H$54)),0) -> 0 | F78: =IF((F112>Assumptions!$H$53)*(E56>0),-MIN(E56,FLOOR(MAX(0,F112-Assumptions!$H$52),Assumptions!$H$54)),0) -> 0 | G78: =IF((G112>Assumptions!$H$53)*(F56>0),-MIN(F56,FLOOR(MAX(0,G112-Assumptions!$H$52),Assumptions!$H$54)),0) -> 0 | H78: =IF((H112>Assumptions!$H$53)*(G56>0),-MIN(G56,FLOOR(MAX(0,H112-Assumptions!$H$52),Assumptions!$H$54)),0) -> 0 | I78: =IF((I112>Assumptions!$H$53)*(H56>0),-MIN(H56,FLOOR(MAX(0,I112-Assumptions!$H$52),Assumptions!$H$54)),0) -> 0 | J78: =IF((J112>Assumptions!$H$53)*(I56>0),-MIN(I56,FLOOR(MAX(0,J112-Assumptions!$H$52),Assumptions!$H$54)),0) -> -95000 | K78: =IF((K112>Assumptions!$H$53)*(J56>0),-MIN(J56,FLOOR(MAX(0,K112-Assumptions!$H$52),Assumptions!$H$54)),0) -> -102000 | ... O78: =IF((O112>Assumptions!$H$53)*(N56>0),-MIN(N56,FLOOR(MAX(0,O112-Assumptions!$H$52),Assumptions!$H$54)),0) -> 0 | P78: =SUM(D78:O78) -> -197000
A79: contrib | B79: Capital contributions from head office (financing requirement) | D79: =IF(D112+D77<Assumptions!$H$51,CEILING(MAX(0,Assumptions!$H$52-D112-D77),Assumptions!$H$54),0) -> 0 | E79: =IF(E112+E77<Assumptions!$H$51,CEILING(MAX(0,Assumptions!$H$52-E112-E77),Assumptions!$H$54),0) -> 0 | F79: =IF(F112+F77<Assumptions!$H$51,CEILING(MAX(0,Assumptions!$H$52-F112-F77),Assumptions!$H$54),0) -> 0 | G79: =IF(G112+G77<Assumptions!$H$51,CEILING(MAX(0,Assumptions!$H$52-G112-G77),Assumptions!$H$54),0) -> 0 | H79: =IF(H112+H77<Assumptions!$H$51,CEILING(MAX(0,Assumptions!$H$52-H112-H77),Assumptions!$H$54),0) -> 0 | I79: =IF(I112+I77<Assumptions!$H$51,CEILING(MAX(0,Assumptions!$H$52-I112-I77),Assumptions!$H$54),0) -> 0 | J79: =IF(J112+J77<Assumptions!$H$51,CEILING(MAX(0,Assumptions!$H$52-J112-J77),Assumptions!$H$54),0) -> 0 | K79: =IF(K112+K77<Assumptions!$H$51,CEILING(MAX(0,Assumptions!$H$52-K112-K77),Assumptions!$H$54),0) -> 0 | ... O79: =IF(O112+O77<Assumptions!$H$51,CEILING(MAX(0,Assumptions!$H$52-O112-O77),Assumptions!$H$54),0) -> 0 | P79: =SUM(D79:O79) -> 0
A80: dist | B80: Distributions to head office | D80: =IF(Drivers!D22*(D56<0.005)*(D112+D77+D78+D79>Assumptions!$H$55),-FLOOR(MAX(0,D112+D77+D78+D79-Assumptions!$H$56),1000),0) -> 0 | E80: =IF(Drivers!E22*(E56<0.005)*(E112+E77+E78+E79>Assumptions!$H$55),-FLOOR(MAX(0,E112+E77+E78+E79-Assumptions!$H$56),1000),0) -> 0 | F80: =IF(Drivers!F22*(F56<0.005)*(F112+F77+F78+F79>Assumptions!$H$55),-FLOOR(MAX(0,F112+F77+F78+F79-Assumptions!$H$56),1000),0) -> 0 | G80: =IF(Drivers!G22*(G56<0.005)*(G112+G77+G78+G79>Assumptions!$H$55),-FLOOR(MAX(0,G112+G77+G78+G79-Assumptions!$H$56),1000),0) -> 0 | H80: =IF(Drivers!H22*(H56<0.005)*(H112+H77+H78+H79>Assumptions!$H$55),-FLOOR(MAX(0,H112+H77+H78+H79-Assumptions!$H$56),1000),0) -> 0 | I80: =IF(Drivers!I22*(I56<0.005)*(I112+I77+I78+I79>Assumptions!$H$55),-FLOOR(MAX(0,I112+I77+I78+I79-Assumptions!$H$56),1000),0) -> 0 | J80: =IF(Drivers!J22*(J56<0.005)*(J112+J77+J78+J79>Assumptions!$H$55),-FLOOR(MAX(0,J112+J77+J78+J79-Assumptions!$H$56),1000),0) -> 0 | K80: =IF(Drivers!K22*(K56<0.005)*(K112+K77+K78+K79>Assumptions!$H$55),-FLOOR(MAX(0,K112+K77+K78+K79-Assumptions!$H$56),1000),0) -> 0 | ... O80: =IF(Drivers!O22*(O56<0.005)*(O112+O77+O78+O79>Assumptions!$H$55),-FLOOR(MAX(0,O112+O77+O78+O79-Assumptions!$H$56),1000),0) -> 0 | P80: =SUM(D80:O80) -> 0
A81: cff | B81: Net cash from (used in) financing activities | D81: =D76+D77+D78+D79+D80 -> -4166.67 | E81: =E76+E77+E78+E79+E80 -> -4166.67 | F81: =F76+F77+F78+F79+F80 -> -4166.67 | G81: =G76+G77+G78+G79+G80 -> 126833.33 | H81: =H76+H77+H78+H79+H80 -> 61833.33 | I81: =I76+I77+I78+I79+I80 -> -4166.67 | J81: =J76+J77+J78+J79+J80 -> -99166.67 | K81: =K76+K77+K78+K79+K80 -> -106166.67 | ... O81: =O76+O77+O78+O79+O80 -> -4166.67 | P81: =SUM(D81:O81) -> -50000.04
A82: net_change | B82: Net change in cash | D82: =D74+D75+D81 -> -82364.159 | E82: =E74+E75+E81 -> -70863.788 | F82: =F74+F75+F81 -> -84875.499 | G82: =G74+G75+G81 -> -15720.35 | H82: =H74+H75+H81 -> -203.72464 | I82: =I74+I75+I81 -> -10187.973 | J82: =J74+J75+J81 -> 9978.935 | K82: =K74+K75+K81 -> 94239.358 | ... O82: =O74+O75+O81 -> -58046.443 | P82: =SUM(D82:O82) -> -12614.187
A84: CHECKS
A85: check_bs | B85: Check: assets - liabilities - equity (must be 0) | C85: =Hist_BS!$AI$31 -> 0 | D85: =D51-D65 -> 0 | E85: =E51-E65 -> 0 | F85: =F51-F65 -> 0 | G85: =G51-G65 -> 0 | H85: =H51-H65 -> 0 | I85: =I51-I65 -> 0 | J85: =J51-J65 -> 0 | K85: =K51-K65 -> 0 | ... O85: =O51-O65 -> 0
A86: check_cash | B86: Check: CF closing cash - BS cash (must be 0) | D86: =C41+D82-D41 -> 0 | E86: =D41+E82-E41 -> 0 | F86: =E41+F82-F41 -> 0 | G86: =F41+G82-G41 -> 0 | H86: =G41+H82-H41 -> 0 | I86: =H41+I82-I41 -> 0 | J86: =I41+J82-J41 -> 0 | K86: =J41+K82-K41 -> 0 | ... O86: =N41+O82-O41 -> 0
A88: SUPPORTING SCHEDULES - revenue & cost build
A89: units | B89: E-bike units sold (net of returns) | D89: =Drivers!D6*Assumptions!$H$8*(1+Assumptions!$H$9)^Assumptions!$H$10 -> 50.433529 | E89: =Drivers!E6*Assumptions!$H$8*(1+Assumptions!$H$9)^Assumptions!$H$10 -> 37.28996 | F89: =Drivers!F6*Assumptions!$H$8*(1+Assumptions!$H$9)^Assumptions!$H$10 -> 31.442638 | G89: =Drivers!G6*Assumptions!$H$8*(1+Assumptions!$H$9)^Assumptions!$H$10 -> 23.546461 | H89: =Drivers!H6*Assumptions!$H$8*(1+Assumptions!$H$9)^Assumptions!$H$10 -> 22.673747 | I89: =Drivers!I6*Assumptions!$H$8*(1+Assumptions!$H$9)^Assumptions!$H$10 -> 49.435386 | J89: =Drivers!J6*Assumptions!$H$8*(1+Assumptions!$H$9)^Assumptions!$H$10 -> 111.31885 | K89: =Drivers!K6*Assumptions!$H$8*(1+Assumptions!$H$9)^Assumptions!$H$10 -> 132.99826 | ... O89: =Drivers!O6*Assumptions!$H$8*(1+Assumptions!$H$9)^Assumptions!$H$10 -> 74.610759 | P89: =SUM(D89:O89) -> 889.93545
A90: asp | B90: Average e-bike list price | D90: =Assumptions!$H$25*(1+Assumptions!$H$9) -> 2591.8897 | E90: =Assumptions!$H$25*(1+Assumptions!$H$9) -> 2591.8897 | F90: =Assumptions!$H$25*(1+Assumptions!$H$9) -> 2591.8897 | G90: =Assumptions!$H$25*(1+Assumptions!$H$9) -> 2591.8897 | H90: =Assumptions!$H$25*(1+Assumptions!$H$9) -> 2591.8897 | I90: =Assumptions!$H$25*(1+Assumptions!$H$9) -> 2591.8897 | J90: =Assumptions!$H$25*(1+Assumptions!$H$9) -> 2591.8897 | K90: =Assumptions!$H$25*(1+Assumptions!$H$9) -> 2591.8897 | ... O90: =Assumptions!$H$25*(1+Assumptions!$H$9) -> 2591.8897
A91: disc_rate | B91: Bike discount rate | D91: =Assumptions!$H$26+Assumptions!$H$11 -> 0.023285991 | E91: =Assumptions!$H$26+Assumptions!$H$11 -> 0.023285991 | F91: =Assumptions!$H$26+Assumptions!$H$11 -> 0.023285991 | G91: =Assumptions!$H$26+Assumptions!$H$11 -> 0.023285991 | H91: =Assumptions!$H$26+Assumptions!$H$11 -> 0.023285991 | I91: =Assumptions!$H$26+Assumptions!$H$11 -> 0.023285991 | J91: =Assumptions!$H$26+Assumptions!$H$11 -> 0.023285991 | K91: =Assumptions!$H$26+Assumptions!$H$11 -> 0.023285991 | ... O91: =Assumptions!$H$26+Assumptions!$H$11 -> 0.023285991
A92: bike_net | B92: Net e-bike revenue (after discounts & returns) | D92: =D89*D90*(1-D91) -> 127674.24 | E92: =E89*E90*(1-E91) -> 94400.836 | F92: =F89*F90*(1-F91) -> 79598.138 | G92: =G89*G90*(1-G91) -> 59608.689 | H92: =H89*H90*(1-H91) -> 57399.382 | I92: =I89*I90*(1-I91) -> 125147.41 | J92: =J89*J90*(1-J91) -> 281807.57 | K92: =K89*K90*(1-K91) -> 336689.74 | ... O92: =O89*O90*(1-O91) -> 188879.74 | P92: =SUM(D92:O92) -> 2252902.7
A93: acc_net | B93: Net accessories & parts revenue | D93: =Drivers!D7*Assumptions!$H$8*(1+Assumptions!$H$9) -> 22723.518 | E93: =Drivers!E7*Assumptions!$H$8*(1+Assumptions!$H$9) -> 12180.322 | F93: =Drivers!F7*Assumptions!$H$8*(1+Assumptions!$H$9) -> 15285.082 | G93: =Drivers!G7*Assumptions!$H$8*(1+Assumptions!$H$9) -> 15178.059 | H93: =Drivers!H7*Assumptions!$H$8*(1+Assumptions!$H$9) -> 11141.182 | I93: =Drivers!I7*Assumptions!$H$8*(1+Assumptions!$H$9) -> 20438.756 | J93: =Drivers!J7*Assumptions!$H$8*(1+Assumptions!$H$9) -> 28791.859 | K93: =Drivers!K7*Assumptions!$H$8*(1+Assumptions!$H$9) -> 36900.546 | ... O93: =Drivers!O7*Assumptions!$H$8*(1+Assumptions!$H$9) -> 28765.636 | P93: =SUM(D93:O93) -> 315337.68
A94: merch_cogs | B94: Merchandise COGS (memo) | D94: =D16+D17 -> -105183.68 | E94: =E16+E17 -> -75081.232 | F94: =F16+F17 -> -66227.439 | G94: =G16+G17 -> -51768.173 | H94: =H16+H17 -> -47826.787 | I94: =I16+I17 -> -102033.65 | J94: =J16+J17 -> -219727.66 | K94: =K16+K17 -> -263976.04 | ... O94: =O16+O17 -> -152783.18 | P94: =SUM(D94:O94) -> -1806186.1
A95: commission | B95: Sales commission (memo) | D95: =Assumptions!$H$35*D92 -> 1915.1136 | E95: =Assumptions!$H$35*E92 -> 1416.0125 | F95: =Assumptions!$H$35*F92 -> 1193.9721 | G95: =Assumptions!$H$35*G92 -> 894.13034 | H95: =Assumptions!$H$35*H92 -> 860.99073 | I95: =Assumptions!$H$35*I92 -> 1877.2111 | J95: =Assumptions!$H$35*J92 -> 4227.1135 | K95: =Assumptions!$H$35*K92 -> 5050.3462 | ... O95: =Assumptions!$H$35*O92 -> 2833.1962 | P95: =SUM(D95:O95) -> 33793.54
A97: SUPPORTING SCHEDULES - inventory investment
A98: inv_target | B98: Inventory target (cover x avg next-2-month merchandise COGS) | D98: =-Drivers!D19*Assumptions!$H$17*(E94+F94)/2 -> 359221.27 | E98: =-Drivers!E19*Assumptions!$H$17*(F94+G94)/2 -> 382137.91 | F98: =-Drivers!F19*Assumptions!$H$17*(G94+H94)/2 -> 458205.2 | G98: =-Drivers!G19*Assumptions!$H$17*(H94+I94)/2 -> 498659.89 | H98: =-Drivers!H19*Assumptions!$H$17*(I94+J94)/2 -> 517223.93 | I98: =-Drivers!I19*Assumptions!$H$17*(J94+K94)/2 -> 587764.91 | J98: =-Drivers!J19*Assumptions!$H$17*(K94+L94)/2 -> 509805.87 | K98: =-Drivers!K19*Assumptions!$H$17*(L94+M94)/2 -> 370357.18 | ... M98: =-Drivers!M19*Assumptions!$H$17*(N94+O94)/2 -> 325730.4 | N98: =-Drivers!N19*Assumptions!$H$17*(O94+D94)/2 -> 345507.63 | O98: =-Drivers!O19*Assumptions!$H$17*(D94+E94)/2 -> 361375.2
A99: purchases | B99: Inventory purchases at cost | D99: =MAX(0,D98-C43-D94-D18) -> 122273.39 | E99: =MAX(0,E98-D43-E94-E18) -> 98300.033 | F99: =MAX(0,F98-E43-F94-F18) -> 142561.26 | G99: =MAX(0,G98-F43-G94-G18) -> 92431.202 | H99: =MAX(0,H98-G43-H94-H18) -> 66583.308 | I99: =MAX(0,I98-H43-I94-I18) -> 172985.26 | J99: =MAX(0,J98-I43-J94-J18) -> 142652.91 | K99: =MAX(0,K98-J43-K94-K18) -> 125589.72 | ... O99: =MAX(0,O98-N43-O94-O18) -> 169265.62 | P99: =SUM(D99:O99) -> 1832275.3
A101: SUPPORTING SCHEDULES - working capital
A102: prepaid_ins | B102: Prepaid insurance (memo) | C102: =Hist_Balances!$AJ$13 -> 7463.04 | D102: =C102+Drivers!D15-Drivers!D14 -> 4975.36 | E102: =D102+Drivers!E15-Drivers!E14 -> 2487.68 | F102: =E102+Drivers!F15-Drivers!F14 -> 0 | G102: =F102+Drivers!G15-Drivers!G14 -> 28459.059 | H102: =G102+Drivers!H15-Drivers!H14 -> 25871.872 | I102: =H102+Drivers!I15-Drivers!I14 -> 23284.685 | J102: =I102+Drivers!J15-Drivers!J14 -> 20697.498 | K102: =J102+Drivers!K15-Drivers!K14 -> 18110.31 | ... O102: =N102+Drivers!O15-Drivers!O14 -> 7761.5616
A103: deposits | B103: Supplier deposits (memo) | C103: =Hist_Balances!$AJ$14 -> 19329.82 | D103: =Assumptions!$H$41*D99 -> 19130.824 | E103: =Assumptions!$H$41*E99 -> 15379.967 | F103: =Assumptions!$H$41*F99 -> 22305.053 | G103: =Assumptions!$H$41*G99 -> 14461.733 | H103: =Assumptions!$H$41*H99 -> 10417.586 | I103: =Assumptions!$H$41*I99 -> 27065.175 | J103: =Assumptions!$H$41*J99 -> 22319.393 | K103: =Assumptions!$H$41*K99 -> 19649.695 | ... O103: =Assumptions!$H$41*O99 -> 26483.202
A104: gst_net | B104: Net GST payable / (recoverable) (memo) | C104: =-(Hist_Balances!$AJ$15+Hist_Balances!$AJ$23) -> 11736.86 | D104: =C104+Assumptions!$H$45*(D15-(D99-D19+Drivers!D11+Drivers!D12+Drivers!D13+Drivers!D16-D28-D30+Drivers!D17))-D105 -> 1310.4338 | E104: =D104+Assumptions!$H$45*(E15-(E99-E19+Drivers!E11+Drivers!E12+Drivers!E13+Drivers!E16-E28-E30+Drivers!E17))-E105 -> 922.89483 | F104: =E104+Assumptions!$H$45*(F15-(F99-F19+Drivers!F11+Drivers!F12+Drivers!F13+Drivers!F16-F28-F30+Drivers!F17))-F105 -> -2593.7451 | G104: =F104+Assumptions!$H$45*(G15-(G99-G19+Drivers!G11+Drivers!G12+Drivers!G13+Drivers!G16-G28-G30+Drivers!G17))-G105 -> -1717.2372 | H104: =G104+Assumptions!$H$45*(H15-(H99-H19+Drivers!H11+Drivers!H12+Drivers!H13+Drivers!H16-H28-H30+Drivers!H17))-H105 -> -1859.0929 | I104: =H104+Assumptions!$H$45*(I15-(I99-I19+Drivers!I11+Drivers!I12+Drivers!I13+Drivers!I16-I28-I30+Drivers!I17))-I105 -> -3623.107 | J104: =I104+Assumptions!$H$45*(J15-(J99-J19+Drivers!J11+Drivers!J12+Drivers!J13+Drivers!J16-J28-J30+Drivers!J17))-J105 -> 9399.9864 | K104: =J104+Assumptions!$H$45*(K15-(K99-K19+Drivers!K11+Drivers!K12+Drivers!K13+Drivers!K16-K28-K30+Drivers!K17))-K105 -> 23046.133 | ... O104: =N104+Assumptions!$H$45*(O15-(O99-O19+Drivers!O11+Drivers!O12+Drivers!O13+Drivers!O16-O28-O30+Drivers!O17))-O105 -> 10878.96
A105: gst_remit | B105: GST remitted for prior quarter (memo) | D105: =IF(Drivers!D23,C104,0) -> 11736.86 | E105: =IF(Drivers!E23,D104,0) -> 0 | F105: =IF(Drivers!F23,E104,0) -> 0 | G105: =IF(Drivers!G23,F104,0) -> -2593.7451 | H105: =IF(Drivers!H23,G104,0) -> 0 | I105: =IF(Drivers!I23,H104,0) -> 0 | J105: =IF(Drivers!J23,I104,0) -> -3623.107 | K105: =IF(Drivers!K23,J104,0) -> 0 | ... O105: =IF(Drivers!O23,N104,0) -> 0 | P105: =SUM(D105:O105) -> 38668.696
A106: ap_trade | B106: Trade payables - inventory & parts (memo) | C106: =-Hist_Balances!$AJ$20 -> 157952.65 | D106: =(Assumptions!$H$42+Assumptions!$H$15)/30.4*(D99-D19)*(1+Assumptions!$H$45) -> 112446.52 | E106: =(Assumptions!$H$42+Assumptions!$H$15)/30.4*(E99-E19)*(1+Assumptions!$H$45) -> 88472.748 | F106: =(Assumptions!$H$42+Assumptions!$H$15)/30.4*(F99-F19)*(1+Assumptions!$H$45) -> 125040 | G106: =(Assumptions!$H$42+Assumptions!$H$15)/30.4*(G99-G19)*(1+Assumptions!$H$45) -> 85189.841 | H106: =(Assumptions!$H$42+Assumptions!$H$15)/30.4*(H99-H19)*(1+Assumptions!$H$45) -> 64601.343 | I106: =(Assumptions!$H$42+Assumptions!$H$15)/30.4*(I99-I19)*(1+Assumptions!$H$45) -> 158195.41 | J106: =(Assumptions!$H$42+Assumptions!$H$15)/30.4*(J99-J19)*(1+Assumptions!$H$45) -> 136355.95 | K106: =(Assumptions!$H$42+Assumptions!$H$15)/30.4*(K99-K19)*(1+Assumptions!$H$45) -> 123045.91 | ... O106: =(Assumptions!$H$42+Assumptions!$H$15)/30.4*(O99-O19)*(1+Assumptions!$H$45) -> 154525.37
A107: ap_opex | B107: Operating-vendor payables (memo) | C107: =-Hist_Balances!$AJ$21 -> 27972.25 | D107: =Assumptions!$H$43*((Drivers!D12+Drivers!D13+Drivers!D16-D28-D30)*(1+Assumptions!$H$45)-D29) -> 23708.086 | E107: =Assumptions!$H$43*((Drivers!E12+Drivers!E13+Drivers!E16-E28-E30)*(1+Assumptions!$H$45)-E29) -> 21149.107 | F107: =Assumptions!$H$43*((Drivers!F12+Drivers!F13+Drivers!F16-F28-F30)*(1+Assumptions!$H$45)-F29) -> 23641.809 | G107: =Assumptions!$H$43*((Drivers!G12+Drivers!G13+Drivers!G16-G28-G30)*(1+Assumptions!$H$45)-G29) -> 21904.58 | H107: =Assumptions!$H$43*((Drivers!H12+Drivers!H13+Drivers!H16-H28-H30)*(1+Assumptions!$H$45)-H29) -> 21503.852 | I107: =Assumptions!$H$43*((Drivers!I12+Drivers!I13+Drivers!I16-I28-I30)*(1+Assumptions!$H$45)-I29) -> 29171.612 | J107: =Assumptions!$H$43*((Drivers!J12+Drivers!J13+Drivers!J16-J28-J30)*(1+Assumptions!$H$45)-J29) -> 33151.708 | K107: =Assumptions!$H$43*((Drivers!K12+Drivers!K13+Drivers!K16-K28-K30)*(1+Assumptions!$H$45)-K29) -> 34474.673 | ... O107: =Assumptions!$H$43*((Drivers!O12+Drivers!O13+Drivers!O16-O28-O30)*(1+Assumptions!$H$45)-O29) -> 29138.509
A108: accrued_pay | B108: Accrued payroll (memo) | C108: =-Hist_Balances!$AJ$22 -> 28360.02 | D108: =Assumptions!$H$44*(Drivers!D9+D95+Drivers!D10) -> 20445.672 | E108: =Assumptions!$H$44*(Drivers!E9+E95+Drivers!E10) -> 18998.748 | F108: =Assumptions!$H$44*(Drivers!F9+F95+Drivers!F10) -> 18887.728 | G108: =Assumptions!$H$44*(Drivers!G9+G95+Drivers!G10) -> 19935.179 | H108: =Assumptions!$H$44*(Drivers!H9+H95+Drivers!H10) -> 18122.548 | I108: =Assumptions!$H$44*(Drivers!I9+I95+Drivers!I10) -> 20426.722 | J108: =Assumptions!$H$44*(Drivers!J9+J95+Drivers!J10) -> 30015.643 | K108: =Assumptions!$H$44*(Drivers!K9+K95+Drivers!K10) -> 30427.26 | ... O108: =Assumptions!$H$44*(Drivers!O9+O95+Drivers!O10) -> 29318.684
...

Sheet Scenario_Results
A1: ⚠ SIMULATED FINANCIAL INFORMATION - illustrative Calgary management accounts, not Prairie Pulse E-Bikes' actual financials. Synthetic data generated for a VisiVault Analytics proof of concept (seed 20240101).
A2: Scenario comparison and sensitivity analysis (values computed by the Python engine at build time)
A3: The Forecast sheet recalculates live for the scenario selected on Assumptions; this sheet stores all three for comparison.
B5: Conservative | C5: Base | D5: Optimistic
A6: net_revenue | B6: 3026573.3 | C6: 3274439.3 | D6: 3520752.9
A7: gross_profit | B7: 1041564.6 | C7: 1186160.9 | D7: 1364287.1
A8: gross_margin_pct | B8: 34.413989 | C8: 36.224855 | D8: 38.749866
A9: ebitda | B9: -46949.881 | C9: 89356.522 | D9: 275694.57
A10: ebit | B10: -86773.511 | C10: 49532.892 | D10: 235870.94
A11: pbt | B11: -97641.376 | C11: 40683.193 | D11: 229035.49
A12: net_income | B12: -97641.376 | C12: 33876.436 | D12: 178907.7
A13: net_margin_pct | B13: -3.2261362 | C13: 1.0345721 | D13: 5.0815183
A14: cfo | B14: -118468.27 | C14: 55385.853 | D14: 308578.38
A15: closing_cash | B15: 167991.13 | C15: 341845.25 | D15: 595037.78
A16: min_cash | B16: 61489.683 | C16: 90243.946 | D16: 100967.47
A17: peak_revolver | B17: 237000 | C17: 197000 | D17: 101000
... A25: max_abs_cash_check | B25: 0 | C25: 0 | D25: 0
A28: Sensitivity analysis (one driver at a time vs Base)
A29: driver | B29: case | C29: value | D29: net_income | E29: delta_net_income | F29: closing_cash | G29: delta_closing_cash | H29: min_cash | I29: peak_revolver | J29: financing_requirement | K29: delta_financing_requirement
A30: Product demand (-/+10%) | B30: downside | C30: 0.9 | D30: -12575.257 | E30: -46451.693 | F30: 312397.12 | G30: -29448.132 | H30: 87768.539 | I30: 158000 | J30: 158000 | K30: -39000
A31: Product demand (-/+10%) | B31: upside | C31: 1.1 | D31: 74885.442 | E31: 41009.006 | F31: 371293.38 | G31: 29448.132 | H31: 84543.571 | I31: 236000 | J31: 236000 | K31: 39000
A32: Merchandise gross margin (-/+2 pts) | B32: downside | C32: -0.02 | D32: -15092.411 | E32: -48968.848 | F32: 278387.16 | G32: -63458.09 | H32: 86932.248 | I32: 222000 | J32: 222000 | K32: 25000
A33: Merchandise gross margin (-/+2 pts) | B33: upside | C33: 0.02 | D33: 76823.651 | E33: 42947.215 | F33: 405303.34 | G33: 63458.09 | H33: 93555.644 | I33: 172000 | J33: 172000 | K33: -25000
A34: Inventory / supplier costs (+/-5%) | B34: downside | C34: 0.05 | D34: -57381.149 | E34: -91257.586 | F34: 230320.11 | G34: -111525.14 | H34: 82821.057 | I34: 241000 | J34: 241000 | K34: 44000
A35: Inventory / supplier costs (+/-5%) | B35: upside | C35: -0.05 | D35: 109382.48 | E35: 75506.046 | F35: 453365.85 | G35: 111520.6 | H35: 96018.734 | I35: 153000 | J35: 153000 | K35: -44000
A36: Supplier payment terms (-/+10 days) | B36: downside | C36: -10 | D36: 33201.499 | E36: -674.93708 | F36: 277981.35 | G36: -63863.899 | H36: 65387.411 | I36: 272000 | J36: 272000 | K36: 75000
A37: Supplier payment terms (-/+10 days) | B37: upside | C37: 10 | D37: 34376.519 | E37: 500.08292 | F37: 405482.07 | G37: 63636.816 | H37: 100199.18 | I37: 171000 | J37: 171000 | K37: -26000
A38: Interest rates (+/-100 bps) | B38: downside | C38: 0.01 | D38: 32771.904 | E38: -1104.5319 | F38: 340410.8 | G38: -1434.4571 | H38: 90454.822 | I38: 198000 | J38: 198000 | K38: 1000
A39: Interest rates (+/-100 bps) | B39: upside | C39: -0.01 | D39: 34971.407 | E39: 1094.9711 | F39: 343267.29 | G39: 1422.0404 | H39: 91027.695 | I39: 197000 | J39: 197000 | K39: 0
A40: Service revenue (-/+15%) | B40: downside | C40: 0.85 | D40: -40310.902 | E40: -74187.338 | F40: 259347.74 | G40: -82497.516 | H40: 82360.132 | I40: 218000 | J40: 218000 | K40: 21000
A41: Service revenue (-/+15%) | B41: upside | C41: 1.15 | D41: 96238.392 | E41: 62361.956 | F41: 424338.23 | G41: 82492.974 | H41: 98127.76 | I41: 176000 | J41: 176000 | K41: -21000
A44: LIVE: active scenario (formulas on the Forecast sheet)
A45: Net revenue | B45: =SUM(Forecast!D15:O15) -> 3274439.3
A46: Net income | B46: =SUM(Forecast!D38:O38) -> 33876.436
A47: Closing cash Sep-2027 | B47: =Forecast!O41 -> 341845.25
A48: Minimum month-end cash | B48: =MIN(Forecast!D41:O41) -> 90243.946
A49: Peak revolver | B49: =MAX(0,MAX(Forecast!D56:O56)) -> 197000
A50: Head-office contributions required | B50: =SUM(Forecast!D79:O79) -> 0
A51: Max |balance-sheet check| | B51: =MAX(ABS(MIN(Forecast!D85:O85)),ABS(MAX(Forecast!D85:O85))) -> 0

Sheet Checks
A1: ⚠ SIMULATED FINANCIAL INFORMATION - illustrative Calgary management accounts, not Prairie Pulse E-Bikes' actual financials. Synthetic data generated for a VisiVault Analytics proof of concept (seed 20240101).
A2: Model integrity checks (live formulas - every value must be 0 / TRUE)
A5: Check | B5: Value | C5: Pass?
A6: Trial balance: max |sum of account balances| (Dec-2023 to Sep-2026) | B6: =MAX(ABS(MIN(Hist_Balances!$C$60:$AJ$60)),ABS(MAX(Hist_Balances!$C$60:$AJ$60))) -> 0 | C6: =ABS(B6)<0.01 -> TRUE
A7: Historical balance sheet: max |assets - liabilities - equity| | B7: =MAX(ABS(MIN(Hist_BS!C31:AI31)),ABS(MAX(Hist_BS!C31:AI31))) -> 0 | C7: =ABS(B7)<0.01 -> TRUE
A8: Historical cash flow: max |closing cash - balance-sheet cash| | B8: =MAX(ABS(MIN(Hist_CF!C31:AI31)),ABS(MAX(Hist_CF!C31:AI31))) -> 0 | C8: =ABS(B8)<0.01 -> TRUE
A9: Forecast balance sheet: max |assets - liabilities - equity| | B9: =MAX(ABS(MIN(Forecast!D85:O85)),ABS(MAX(Forecast!D85:O85))) -> 0 | C9: =ABS(B9)<0.01 -> TRUE
A10: Forecast cash flow: max |closing cash - balance-sheet cash| | B10: =MAX(ABS(MIN(Forecast!D86:O86)),ABS(MAX(Forecast!D86:O86))) -> 0 | C10: =ABS(B10)<0.01 -> TRUE
A11: Forecast opening cash = historical closing cash (Sep-2026) | B11: =ROUND(Forecast!C41-Hist_BS!AI6,2) -> 0 | C11: =ABS(B11)<0.01 -> TRUE
A12: ALL CHECKS PASS | C12: =AND(C6:C11) -> TRUE

Sheet Hist_IS
A1: ⚠ SIMULATED FINANCIAL INFORMATION - illustrative Calgary management accounts, not Prairie Pulse E-Bikes' actual financials. Synthetic data generated for a VisiVault Analytics proof of concept (seed 20240101).
A2: Historical income statements - illustrative Calgary management accounts (CAD)
A3: Monthly values from the general ledger; subtotal rows are live formulas. FY columns sum the months.
A5: Line | B5: Key | C5: 2024-01 | D5: 2024-02 | E5: 2024-03 | F5: 2024-04 | G5: 2024-05 | H5: 2024-06 | I5: 2024-07 | J5: 2024-08 | K5: 2024-09 | L5: 2024-10 | M5: 2024-11 | N5: 2024-12 | O5: 2025-01 | P5: 2025-02 | Q5: 2025-03 | R5: 2025-04 | S5: 2025-05 | T5: 2025-06 | U5: 2025-07 | V5: 2025-08 | W5: 2025-09 | X5: 2025-10 | Y5: 2025-11 | Z5: 2025-12 | AA5: 2026-01 | AB5: 2026-02 | AC5: 2026-03 | AD5: 2026-04 | AE5: 2026-05 | AF5: 2026-06 | AG5: 2026-07 | AH5: 2026-08 | AI5: 2026-09 | AJ5: FY2024 | AK5: FY2025 | AL5: YTD Sep-2026
A6: Bicycle sales revenue | B6: bike_rev | C6: 50428.97 | D6: 50339 | E6: 122816.92 | F6: 295515.84 | G6: 357640.71 | H6: 310458.84 | I6: 318145.79 | J6: 272296.86 | K6: 160877.91 | L6: 122879.93 | M6: 104834.95 | N6: 104174.93 | O6: 50401.97 | P6: 43633.99 | Q6: 74070.97 | R6: 312186.78 | S6: 335848.82 | T6: 330083.79 | U6: 295981.86 | V6: 283498.84 | W6: 202701.83 | X6: 106321.92 | Y6: 106112.95 | Z6: 67477.95 | AA6: 73577.94 | AB6: 68797.96 | AC6: 138062.94 | AD6: 263022.79 | AE6: 396934.75 | AF6: 346100.81 | AG6: 325802.8 | AH6: 296693.84 | AI6: 172304.84 | AJ6: =SUM(C6:N6) -> 2270410.7 | AK6: =SUM(O6:Z6) -> 2208321.7 | AL6: =SUM(AA6:AI6) -> 2081298.7
A7: Accessories and parts revenue | B7: acc_rev | C7: 14013.4 | D7: 12961.43 | E7: 17131.41 | F7: 22302.58 | G7: 26287.4 | H7: 26019.84 | I7: 27524.82 | J7: 25421.63 | K7: 23408.79 | L7: 24925.3 | M7: 14944.99 | N7: 14152.8 | O7: 13672.46 | P7: 11536.17 | Q7: 16715.07 | R7: 21213.1 | S7: 35951.09 | T7: 29502.52 | U7: 21874.55 | V7: 23052.52 | W7: 21382.51 | X7: 22891.97 | Y7: 13785.14 | Z7: 13690.19 | AA7: 17379.73 | AB7: 9238.57 | AC7: 15903.38 | AD7: 30050.25 | AE7: 36211.79 | AF7: 39905.55 | AG7: 29787.37 | AH7: 29177.31 | AI7: 22361.65 | AJ7: =SUM(C7:N7) -> 249094.39 | AK7: =SUM(O7:Z7) -> 245267.29 | AL7: =SUM(AA7:AI7) -> 230015.6
A8: Maintenance and repair revenue | B8: svc_rev | C8: 18008.66 | D8: 40421.83 | E8: 34718.13 | F8: 58779.15 | G8: 64423.56 | H8: 53391.19 | I8: 69612.24 | J8: 60741.73 | K8: 55917.6 | L8: 34240.23 | M8: 28237.43 | N8: 25057.94 | O8: 29443.57 | P8: 34996.03 | Q8: 51862.99 | R8: 64747.99 | S8: 62566.04 | T8: 65529.96 | U8: 64189.22 | V8: 67399.29 | W8: 68839.2 | X8: 40982.84 | Y8: 25940.5 | Z8: 21186.53 | AA8: 33117.89 | AB8: 35517.54 | AC8: 55989.06 | AD8: 71677.87 | AE8: 79081.59 | AF8: 85342.71 | AG8: 76772.97 | AH8: 68353.64 | AI8: 44325.8 | AJ8: =SUM(C8:N8) -> 543549.69 | AK8: =SUM(O8:Z8) -> 597684.16 | AL8: =SUM(AA8:AI8) -> 550179.07
A9: Gross revenue | B9: gross_rev | C9: =C6+C7+C8 -> 82451.03 | D9: =D6+D7+D8 -> 103722.26 | E9: =E6+E7+E8 -> 174666.46 | F9: =F6+F7+F8 -> 376597.57 | G9: =G6+G7+G8 -> 448351.67 | H9: =H6+H7+H8 -> 389869.87 | I9: =I6+I7+I8 -> 415282.85 | J9: =J6+J7+J8 -> 358460.22 | ... AI9: =AI6+AI7+AI8 -> 238992.29 | AJ9: =SUM(C9:N9) -> 3063054.7 | AK9: =SUM(O9:Z9) -> 3051273.1 | AL9: =SUM(AA9:AI9) -> 2861493.3
A10: Sales discounts & promotional allowances | B10: discounts | C10: -721.87 | D10: -1044.09 | E10: -2256.85 | F10: -13934.24 | G10: -9471.36 | H10: -7632.92 | I10: -5914.76 | J10: -3959.27 | K10: -3195.07 | L10: -1904.03 | M10: -6328.37 | N10: -3384.44 | O10: -1024.59 | P10: -488.94 | Q10: -1331.5 | R10: -15891.6 | S10: -9656.74 | T10: -7955.35 | U10: -4657.57 | V10: -4897.54 | W10: -3200.12 | X10: -2250.6 | Y10: -4362.38 | Z10: -3198.57 | AA10: -1350.77 | AB10: -1083.3 | AC10: -2320.98 | AD10: -12953.76 | AE10: -9322.12 | AF10: -8742.45 | AG10: -5407.47 | AH10: -6511.39 | AI10: -3389.15 | AJ10: =SUM(C10:N10) -> -59747.27 | AK10: =SUM(O10:Z10) -> -58915.5 | AL10: =SUM(AA10:AI10) -> -51081.39
A11: Sales returns & refunds | B11: returns | C11: -94.98 | D11: -192.47 | E11: -5318.09 | F11: -5077.03 | G11: -7789.39 | H11: -14431.61 | I11: -6553.18 | J11: -11741.96 | K11: -9224.04 | L11: -3975.47 | M11: -189.97 | N11: -4183.13 | O11: -3361.94 | P11: -2429.1 | Q11: -2739.98 | R11: -6092.96 | S11: -14106.22 | T11: -7845 | U11: -9325.97 | V11: -2622.42 | W11: -14089.4 | X11: -6167.93 | Y11: -79.98 | Z11: -699.99 | AA11: -6285.12 | AB11: -5382.96 | AC11: -3772.43 | AD11: -3327.9 | AE11: -11295.93 | AF11: -3243.93 | AG11: -24283.47 | AH11: -6521.67 | AI11: -8514.48 | AJ11: =SUM(C11:N11) -> -68771.32 | AK11: =SUM(O11:Z11) -> -69560.89 | AL11: =SUM(AA11:AI11) -> -72627.89
A12: Sales returns and allowances | B12: returns_allow | C12: =C10+C11 -> -816.85 | D12: =D10+D11 -> -1236.56 | E12: =E10+E11 -> -7574.94 | F12: =F10+F11 -> -19011.27 | G12: =G10+G11 -> -17260.75 | H12: =H10+H11 -> -22064.53 | I12: =I10+I11 -> -12467.94 | J12: =J10+J11 -> -15701.23 | ... AI12: =AI10+AI11 -> -11903.63 | AJ12: =SUM(C12:N12) -> -128518.59 | AK12: =SUM(O12:Z12) -> -128476.39 | AL12: =SUM(AA12:AI12) -> -123709.28
A13: Net revenue | B13: net_rev | C13: =C9+C12 -> 81634.18 | D13: =D9+D12 -> 102485.7 | E13: =E9+E12 -> 167091.52 | F13: =F9+F12 -> 357586.3 | G13: =G9+G12 -> 431090.92 | H13: =H9+H12 -> 367805.34 | I13: =I9+I12 -> 402814.91 | J13: =J9+J12 -> 342758.99 | ... AI13: =AI9+AI12 -> 227088.66 | AJ13: =SUM(C13:N13) -> 2934536.1 | AK13: =SUM(O13:Z13) -> 2922796.7 | AL13: =SUM(AA13:AI13) -> 2737784.1
A14: Cost of goods sold - e-bikes | B14: cogs_bike | C14: -35896.09 | D14: -35449.04 | E14: -82587.84 | F14: -203983.61 | G14: -245508.81 | H14: -208890.53 | I14: -220113.58 | J14: -185421 | K14: -107153.09 | L14: -84130.54 | M14: -73568.87 | N14: -70609.53 | O14: -33766.81 | P14: -28905.42 | Q14: -50352.42 | R14: -214777.2 | S14: -226197.89 | T14: -226926.58 | U14: -204061.93 | V14: -198589.64 | W14: -133690.81 | X14: -72695.89 | Y14: -75043.57 | Z14: -48145.3 | AA14: -46825.8 | AB14: -45738.13 | AC14: -95136.16 | AD14: -182161.14 | AE14: -271694.58 | AF14: -242159.34 | AG14: -211792.24 | AH14: -205132.33 | AI14: -114500.02 | AJ14: =SUM(C14:N14) -> -1553312.5 | AK14: =SUM(O14:Z14) -> -1513153.5 | AL14: =SUM(AA14:AI14) -> -1415139.7
A15: Cost of goods sold - accessories, batteries & parts | B15: cogs_acc | C15: -8277.9 | D15: -7439.31 | E15: -9717.22 | F15: -11763.59 | G15: -14195.76 | H15: -13864.89 | I15: -14555.3 | J15: -13040.05 | K15: -13522.62 | L15: -14635.14 | M15: -7991.11 | N15: -7635.69 | O15: -8028.86 | P15: -6366.57 | Q15: -9537.73 | R15: -10809.52 | S15: -20786.51 | T15: -16580.46 | U15: -11213.99 | V15: -12001.02 | W15: -11460.37 | X15: -11019.86 | Y15: -7619.92 | Z15: -6965.36 | AA15: -10197.62 | AB15: -4397.82 | AC15: -8476.11 | AD15: -17173.77 | AE15: -20205.84 | AF15: -23186.21 | AG15: -16453.63 | AH15: -16078.87 | AI15: -12492.04 | AJ15: =SUM(C15:N15) -> -136638.58 | AK15: =SUM(O15:Z15) -> -132390.17 | AL15: =SUM(AA15:AI15) -> -128661.91
A16: Inventory shrinkage & write-offs | B16: shrink | C16: -574.17 | D16: -899.3 | E16: 0 | F16: -37.69 | G16: -64.98 | H16: -5518.53 | I16: -160.46 | J16: -3011.76 | K16: 0 | L16: -129.99 | M16: 0 | N16: -1751.27 | O16: -12.99 | P16: -2170.71 | Q16: -54.74 | R16: 0 | S16: -1021.27 | T16: -2435.33 | U16: -2938.6 | V16: -1539.3 | W16: -857.49 | X16: -546.38 | Y16: 0 | Z16: -119.58 | AA16: -974.62 | AB16: -1252.43 | AC16: -36.9 | AD16: -117.51 | AE16: -2713.98 | AF16: -97.38 | AG16: -1088.11 | AH16: -123.72 | AI16: -33.79 | AJ16: =SUM(C16:N16) -> -12148.15 | AK16: =SUM(O16:Z16) -> -11696.39 | AL16: =SUM(AA16:AI16) -> -6438.44
A17: Service parts cost | B17: svc_parts | C17: -3787.28 | D17: -10069.1 | E17: -7607.8 | F17: -15482.43 | G17: -15185.34 | H17: -11135.92 | I17: -18078.84 | J17: -13436.63 | K17: -12440.48 | L17: -6309.32 | M17: -6586.36 | N17: -5681.16 | O17: -6374.14 | P17: -9003.93 | Q17: -11463.84 | R17: -15484.19 | S17: -11871.02 | T17: -14041.99 | U17: -14981.76 | V17: -16562.11 | W17: -16685.96 | X17: -8290.97 | Y17: -5388.92 | Z17: -4244.65 | AA17: -6616.94 | AB17: -7293.43 | AC17: -14444.33 | AD17: -18124.7 | AE17: -16288.23 | AF17: -18403.89 | AG17: -16576.44 | AH17: -15391.4 | AI17: -9117.45 | AJ17: =SUM(C17:N17) -> -125800.66 | AK17: =SUM(O17:Z17) -> -134393.48 | AL17: =SUM(AA17:AI17) -> -122256.81
A18: Direct service labour | B18: svc_labour | C18: -3578.93 | D18: -6656.3 | E18: -6061.61 | F18: -8929.38 | G18: -10405.02 | H18: -9081.09 | I18: -10504.23 | J18: -10197.43 | K18: -9427.64 | L18: -6477.54 | M18: -4762.9 | N18: -4339.15 | O18: -5489.53 | P18: -5496.33 | Q18: -8825.06 | R18: -9968.94 | S18: -11182.73 | T18: -11185.3 | U18: -10549.68 | V18: -9918.64 | W18: -10370.61 | X18: -7046.28 | Y18: -4818.17 | Z18: -3861.39 | AA18: -6091.83 | AB18: -6408.44 | AC18: -8623.72 | AD18: -10847.4 | AE18: -13844.71 | AF18: -14671.17 | AG18: -13012.22 | AH18: -11299.53 | AI18: -7689.42 | AJ18: =SUM(C18:N18) -> -90421.22 | AK18: =SUM(O18:Z18) -> -98712.66 | AL18: =SUM(AA18:AI18) -> -92488.44
A19: Cost of goods sold (total cost of sales) | B19: cogs | C19: =C14+C15+C16+C17+C18 -> -52114.37 | D19: =D14+D15+D16+D17+D18 -> -60513.05 | E19: =E14+E15+E16+E17+E18 -> -105974.47 | F19: =F14+F15+F16+F17+F18 -> -240196.7 | G19: =G14+G15+G16+G17+G18 -> -285359.91 | H19: =H14+H15+H16+H17+H18 -> -248490.96 | I19: =I14+I15+I16+I17+I18 -> -263412.41 | J19: =J14+J15+J16+J17+J18 -> -225106.87 | ... AI19: =AI14+AI15+AI16+AI17+AI18 -> -143832.72 | AJ19: =SUM(C19:N19) -> -1918321.1 | AK19: =SUM(O19:Z19) -> -1890346.2 | AL19: =SUM(AA19:AI19) -> -1764985.3
A20: Gross profit | B20: gross_profit | C20: =C13+C19 -> 29519.81 | D20: =D13+D19 -> 41972.65 | E20: =E13+E19 -> 61117.05 | F20: =F13+F19 -> 117389.6 | G20: =G13+G19 -> 145731.01 | H20: =H13+H19 -> 119314.38 | I20: =I13+I19 -> 139402.5 | J20: =J13+J19 -> 117652.12 | ... AI20: =AI13+AI19 -> 83255.94 | AJ20: =SUM(C20:N20) -> 1016215 | AK20: =SUM(O20:Z20) -> 1032450.6 | AL20: =SUM(AA20:AI20) -> 972798.72
A21: Employee compensation | B21: emp_comp | C21: -25102 | D21: -21521.65 | E21: -26373.82 | F21: -38906.53 | G21: -37687.72 | H21: -37204.94 | I21: -39319.38 | J21: -41193.92 | K21: -37563.29 | L21: -32348.89 | M21: -28943.01 | N21: -26978.51 | O21: -27839.13 | P21: -24296.44 | Q21: -30117.87 | R21: -41581.98 | S21: -40504.25 | T21: -42251.7 | U21: -44801.28 | V21: -45130.86 | W21: -42564.59 | X21: -32300.62 | Y21: -32264.41 | Z21: -33111.33 | AA21: -32616.04 | AB21: -28227.27 | AC21: -30525.78 | AD21: -45741.47 | AE21: -46376.03 | AF21: -45938.4 | AG21: -49790.13 | AH21: -49109.38 | AI21: -48506.97 | AJ21: =SUM(C21:N21) -> -393143.66 | AK21: =SUM(O21:Z21) -> -436764.46 | AL21: =SUM(AA21:AI21) -> -376831.47
A22: Rent and occupancy | B22: rent | C22: -19000 | D22: -19000 | E22: -19000 | F22: -19000 | G22: -19000 | H22: -19000 | I22: -19000 | J22: -19000 | K22: -19000 | L22: -19000 | M22: -19000 | N22: -19000 | O22: -19570 | P22: -19570 | Q22: -19570 | R22: -19570 | S22: -19570 | T22: -19570 | U22: -19570 | V22: -19570 | W22: -19570 | X22: -19570 | Y22: -19570 | Z22: -19570 | AA22: -20157.1 | AB22: -20157.1 | AC22: -20157.1 | AD22: -20157.1 | AE22: -20157.1 | AF22: -20157.1 | AG22: -20157.1 | AH22: -20157.1 | AI22: -20157.1 | AJ22: =SUM(C22:N22) -> -228000 | AK22: =SUM(O22:Z22) -> -234840 | AL22: =SUM(AA22:AI22) -> -181413.9
A23: Utilities | B23: utilities | C23: -2360.36 | D23: -2057.47 | E23: -2121.12 | F23: -1632.17 | G23: -1351.04 | H23: -1179.2 | I23: -1236.03 | J23: -1172.67 | K23: -1082.91 | L23: -1527.96 | M23: -2061.48 | N23: -2108.61 | O23: -2040.7 | P23: -2384.02 | Q23: -1802.21 | R23: -1664.26 | S23: -1194.52 | T23: -1253.53 | U23: -1043.81 | V23: -1179.75 | W23: -1181.24 | X23: -1509.15 | Y23: -1811.76 | Z23: -2234.55 | AA23: -2143.58 | AB23: -2034.96 | AC23: -1914.08 | AD23: -1717.99 | AE23: -1187.11 | AF23: -1267.65 | AG23: -1169.37 | AH23: -1052.74 | AI23: -1209.92 | AJ23: =SUM(C23:N23) -> -19891.02 | AK23: =SUM(O23:Z23) -> -19299.5 | AL23: =SUM(AA23:AI23) -> -13697.4
A24: Marketing and advertising | B24: marketing | C24: -4417.58 | D24: -4440.19 | E24: -5347 | F24: -7172.07 | G24: -8346.62 | H24: -8913 | I24: -7877.12 | J24: -7778.9 | K24: -6534.47 | L24: -5064.06 | M24: -5127.59 | N24: -4645.01 | O24: -4851.59 | P24: -4933.17 | Q24: -5633.76 | R24: -6684.59 | S24: -8964.85 | T24: -10034.82 | U24: -8600.36 | V24: -7976.13 | W24: -6644.2 | X24: -5569.78 | Y24: -4786.8 | Z24: -4865.73 | AA24: -4745.15 | AB24: -5122.65 | AC24: -6188.17 | AD24: -7747.15 | AE24: -9846.7 | AF24: -9592.1 | AG24: -8651.76 | AH24: -7808.07 | AI24: -7609.47 | AJ24: =SUM(C24:N24) -> -75663.61 | AK24: =SUM(O24:Z24) -> -79545.78 | AL24: =SUM(AA24:AI24) -> -67311.22
A25: Administrative expenses (incl. insurance & corporate allocation) | B25: admin | C25: -6146.99 | D25: -6017.69 | E25: -6246.87 | F25: -5887.29 | G25: -6104.87 | H25: -6072.98 | I25: -6314.98 | J25: -5929.35 | K25: -5927.33 | L25: -6081.32 | M25: -6046.43 | N25: -6019.16 | O25: -5916.13 | P25: -6159.29 | Q25: -6207.68 | R25: -6144.23 | S25: -6131.09 | T25: -6365.19 | U25: -6082.22 | V25: -6196.03 | W25: -6161.65 | X25: -6005.17 | Y25: -6282.06 | Z25: -6257.43 | AA25: -6324.12 | AB25: -6219.68 | AC25: -6170.09 | AD25: -6432.14 | AE25: -6130.06 | AF25: -6253.67 | AG25: -6402.39 | AH25: -6415.82 | AI25: -6185.8 | AJ25: =SUM(C25:N25) -> -72795.26 | AK25: =SUM(O25:Z25) -> -73908.17 | AL25: =SUM(AA25:AI25) -> -56533.77
A26: Freight and logistics | B26: freight | C26: -5956.58 | D26: -7607.8 | E26: -9502.54 | F26: -4477.19 | G26: -2947.76 | H26: -5840.78 | I26: -8608.72 | J26: -8031.82 | K26: -6709.54 | L26: -3295.93 | M26: -3196.6 | N26: -4718.29 | O26: -3133.22 | P26: -1189.19 | Q26: -2366.78 | R26: -4563.33 | S26: -6477.73 | T26: -9177.9 | U26: -9809.94 | V26: -7132.61 | W26: -6990.8 | X26: -5955.96 | Y26: -3384.49 | Z26: -3579.12 | AA26: -2645.66 | AB26: -5130.06 | AC26: -9283.93 | AD26: -5240.97 | AE26: -4274.93 | AF26: -6694.41 | AG26: -7957.03 | AH26: -7287.39 | AI26: -7160.23 | AJ26: =SUM(C26:N26) -> -70893.55 | AK26: =SUM(O26:Z26) -> -63761.07 | AL26: =SUM(AA26:AI26) -> -55674.61
A27: Merchant and financing fees | B27: fees | C27: -2161.75 | D27: -2113.77 | E27: -3275.96 | F27: -7632.83 | G27: -8788.26 | H27: -7689.63 | I27: -7224.69 | J27: -6928.03 | K27: -4804.57 | L27: -3961.19 | M27: -3093.87 | N27: -2907.67 | O27: -2073.35 | P27: -2072.93 | Q27: -2794.07 | R27: -6900.19 | S27: -7434.83 | T27: -8377.47 | U27: -6516.86 | V27: -6846.94 | W27: -5749.23 | X27: -3194.27 | Y27: -3322.19 | Z27: -2152.27 | AA27: -2678.49 | AB27: -2589.09 | AC27: -4353.35 | AD27: -6431.2 | AE27: -8815.28 | AF27: -8672.5 | AG27: -8182.57 | AH27: -7461.65 | AI27: -4737.63 | AJ27: =SUM(C27:N27) -> -60582.22 | AK27: =SUM(O27:Z27) -> -57434.6 | AL27: =SUM(AA27:AI27) -> -53921.76
A28: Inventory storage, handling & obsolescence | B28: storage | C28: -3495.79 | D28: -4307.77 | E28: -5953.43 | F28: -6289.34 | G28: -4850.16 | H28: -3539.18 | I28: -3168.32 | J28: -3244.49 | K28: -3608.09 | L28: -3807.48 | M28: -3702.76 | N28: -3896.09 | O28: -4268.79 | P28: -4351.27 | Q28: -4234.19 | R28: -3658.83 | S28: -2730.71 | T28: -2365.28 | U28: -2627.56 | V28: -2768.35 | W28: -2870.79 | X28: -3436.66 | Y28: -3808.9 | Z28: -3985.98 | AA28: -4180.88 | AB28: -4626.73 | AC28: -5785.88 | AD28: -6213.27 | AE28: -4975.17 | AF28: -3610.91 | AG28: -3098.35 | AH28: -2900.67 | AI28: -3100.47 | AJ28: =SUM(C28:N28) -> -49862.9 | AK28: =SUM(O28:Z28) -> -41107.31 | AL28: =SUM(AA28:AI28) -> -38492.33
A29: Total operating expenses (before D&A) | B29: opex | C29: =C21+C22+C23+C24+C25+C26+C27+C28 -> -68641.05 | D29: =D21+D22+D23+D24+D25+D26+D27+D28 -> -67066.34 | E29: =E21+E22+E23+E24+E25+E26+E27+E28 -> -77820.74 | F29: =F21+F22+F23+F24+F25+F26+F27+F28 -> -90997.42 | G29: =G21+G22+G23+G24+G25+G26+G27+G28 -> -89076.43 | H29: =H21+H22+H23+H24+H25+H26+H27+H28 -> -89439.71 | I29: =I21+I22+I23+I24+I25+I26+I27+I28 -> -92749.24 | J29: =J21+J22+J23+J24+J25+J26+J27+J28 -> -93279.18 | ... AI29: =AI21+AI22+AI23+AI24+AI25+AI26+AI27+AI28 -> -98667.59 | AJ29: =SUM(C29:N29) -> -970832.22 | AK29: =SUM(O29:Z29) -> -1006660.9 | AL29: =SUM(AA29:AI29) -> -843876.46
A30: EBITDA | B30: ebitda | C30: =C20+C29 -> -39121.24 | D30: =D20+D29 -> -25093.69 | E30: =E20+E29 -> -16703.69 | F30: =F20+F29 -> 26392.18 | G30: =G20+G29 -> 56654.58 | H30: =H20+H29 -> 29874.67 | I30: =I20+I29 -> 46653.26 | J30: =J20+J29 -> 24372.94 | ... AI30: =AI20+AI29 -> -15411.65 | AJ30: =SUM(C30:N30) -> 45382.78 | AK30: =SUM(O30:Z30) -> 25789.68 | AL30: =SUM(AA30:AI30) -> 128922.26
A31: Depreciation and amortization | B31: da | C31: -2619.44 | D31: -2619.44 | E31: -2619.44 | F31: -2619.44 | G31: -2861.11 | H31: -2861.11 | I31: -2861.11 | J31: -2861.11 | K31: -2861.11 | L31: -2861.11 | M31: -2861.11 | N31: -2861.11 | O31: -2861.11 | P31: -2861.11 | Q31: -2861.11 | R31: -3024.44 | S31: -3024.44 | T31: -3092.15 | U31: -3092.15 | V31: -3092.15 | W31: -3092.15 | X31: -3092.15 | Y31: -3092.15 | Z31: -3092.15 | AA31: -3092.15 | AB31: -3092.15 | AC31: -3592.15 | AD31: -3592.15 | AE31: -3712.15 | AF31: -3712.15 | AG31: -3712.15 | AH31: -3712.15 | AI31: -3712.15 | AJ31: =SUM(C31:N31) -> -33366.64 | AK31: =SUM(O31:Z31) -> -36277.26 | AL31: =SUM(AA31:AI31) -> -31929.35
A32: EBIT (operating profit) | B32: ebit | C32: =C30+C31 -> -41740.68 | D32: =D30+D31 -> -27713.13 | E32: =E30+E31 -> -19323.13 | F32: =F30+F31 -> 23772.74 | G32: =G30+G31 -> 53793.47 | H32: =H30+H31 -> 27013.56 | I32: =I30+I31 -> 43792.15 | J32: =J30+J31 -> 21511.83 | ... AI32: =AI30+AI31 -> -19123.8 | AJ32: =SUM(C32:N32) -> 12016.14 | AK32: =SUM(O32:Z32) -> -10487.58 | AL32: =SUM(AA32:AI32) -> 96992.91
A33: Interest expense | B33: interest | C33: -1968.75 | D33: -1935.94 | E33: -2007.38 | F33: -3336.29 | G33: -2623.33 | H33: -1764.11 | I33: -1714.81 | J33: -1647.05 | K33: -1577.28 | L33: -1517.53 | M33: -1423.61 | N33: -1341 | O33: -1279.71 | P33: -1215.8 | Q33: -1437.25 | R33: -1392.75 | S33: -1100 | T33: -1075 | U33: -1050 | V33: -1025 | W33: -985.8 | X33: -938.07 | Y33: -884.03 | Z33: -860.76 | AA33: -837.5 | AB33: -1100.37 | AC33: -1513.1 | AD33: -2002.89 | AE33: -1670.94 | AF33: -721.18 | AG33: -697.92 | AH33: -674.65 | AI33: -651.39 | AJ33: =SUM(C33:N33) -> -22857.08 | AK33: =SUM(O33:Z33) -> -13244.17 | AL33: =SUM(AA33:AI33) -> -9869.94
A34: Profit before tax | B34: pbt | C34: =C32+C33 -> -43709.43 | D34: =D32+D33 -> -29649.07 | E34: =E32+E33 -> -21330.51 | F34: =F32+F33 -> 20436.45 | G34: =G32+G33 -> 51170.14 | H34: =H32+H33 -> 25249.45 | I34: =I32+I33 -> 42077.34 | J34: =J32+J33 -> 19864.78 | ... AI34: =AI32+AI33 -> -19775.19 | AJ34: =SUM(C34:N34) -> -10840.94 | AK34: =SUM(O34:Z34) -> -23731.75 | AL34: =SUM(AA34:AI34) -> 87122.97
A35: Income taxes | B35: tax | C35: 0 | D35: 0 | E35: 0 | F35: 0 | G35: 0 | H35: 0 | I35: 0 | J35: -108.16 | K35: 108.16 | L35: 0 | M35: 0 | N35: 0 | O35: 0 | P35: 0 | Q35: 0 | R35: 0 | S35: 0 | T35: 0 | U35: 0 | V35: 0 | W35: 0 | X35: 0 | Y35: 0 | Z35: 0 | AA35: 0 | AB35: 0 | AC35: 0 | AD35: 0 | AE35: 0 | AF35: 0 | AG35: 0 | AH35: -1997.92 | AI35: 1997.92 | AJ35: =SUM(C35:N35) -> 0 | AK35: =SUM(O35:Z35) -> 0 | AL35: =SUM(AA35:AI35) -> 0
A36: Net income | B36: net_income | C36: =C34+C35 -> -43709.43 | D36: =D34+D35 -> -29649.07 | E36: =E34+E35 -> -21330.51 | F36: =F34+F35 -> 20436.45 | G36: =G34+G35 -> 51170.14 | H36: =H34+H35 -> 25249.45 | I36: =I34+I35 -> 42077.34 | J36: =J34+J35 -> 19756.62 | ... AI36: =AI34+AI35 -> -17777.27 | AJ36: =SUM(C36:N36) -> -10840.94 | AK36: =SUM(O36:Z36) -> -23731.75 | AL36: =SUM(AA36:AI36) -> 87122.97

Sheet Hist_BS
A1: ⚠ SIMULATED FINANCIAL INFORMATION - illustrative Calgary management accounts, not Prairie Pulse E-Bikes' actual financials. Synthetic data generated for a VisiVault Analytics proof of concept (seed 20240101).
A2: Historical balance sheets - month end (CAD)
A3: Monthly values from the general ledger; subtotal rows are live formulas. FY columns sum the months.
A5: Line | B5: Key | C5: 2024-01 | D5: 2024-02 | E5: 2024-03 | F5: 2024-04 | G5: 2024-05 | H5: 2024-06 | I5: 2024-07 | J5: 2024-08 | K5: 2024-09 | L5: 2024-10 | M5: 2024-11 | N5: 2024-12 | O5: 2025-01 | P5: 2025-02 | Q5: 2025-03 | R5: 2025-04 | S5: 2025-05 | T5: 2025-06 | U5: 2025-07 | V5: 2025-08 | W5: 2025-09 | X5: 2025-10 | Y5: 2025-11 | Z5: 2025-12 | AA5: 2026-01 | AB5: 2026-02 | AC5: 2026-03 | AD5: 2026-04 | AE5: 2026-05 | AF5: 2026-06 | AG5: 2026-07 | AH5: 2026-08 | AI5: 2026-09 | AJ5: FY2024 | AK5: FY2025 | AL5: YTD Sep-2026
A6: Cash and cash equivalents | B6: cash | C6: 283273.97 | D6: 73882.28 | E6: 100770.82 | F6: 100625.71 | G6: 190676.27 | H6: 397881.74 | I6: 452726.02 | J6: 436670.57 | K6: 400722.01 | L6: 289312.24 | M6: 241110.08 | N6: 235783.35 | O6: 109112.94 | P6: 100352.47 | Q6: 115450.11 | R6: 241567.77 | S6: 390525.61 | T6: 458978.56 | U6: 478263.05 | V6: 438601.39 | W6: 434335.6 | X6: 322089.65 | Y6: 231958.55 | Z6: 153494.05 | AA6: 72974.76 | AB6: 100304.24 | AC6: 87020.94 | AD6: 100079.8 | AE6: 138781.11 | AF6: 369552.74 | AG6: 422230.39 | AH6: 416997.2 | AI6: 354459.44 | AJ6: =N6 -> 235783.35 | AK6: =Z6 -> 153494.05 | AL6: =AI6 -> 354459.44
A7: Accounts receivable | B7: ar | C7: 9664.48 | D7: 7561.93 | E7: 4671.83 | F7: 35287.21 | G7: 47033.2 | H7: 15714.99 | I7: 32392.77 | J7: 41770.7 | K7: 12652.89 | L7: 14883.88 | M7: 21980.4 | N7: 14872.46 | O7: 10396.04 | P7: 9538.68 | Q7: 4656.46 | R7: 33999.7 | S7: 34772.2 | T7: 53966.9 | U7: 28933.15 | V7: 38289.39 | W7: 19143.53 | X7: 8876.97 | Y7: 2399.3 | Z7: 13184.85 | AA7: 11416.7 | AB7: 14116.49 | AC7: 20854.09 | AD7: 20489.09 | AE7: 30978.85 | AF7: 36066.56 | AG7: 28588.28 | AH7: 30824.05 | AI7: 22724.22 | AJ7: =N7 -> 14872.46 | AK7: =Z7 -> 13184.85 | AL7: =AI7 -> 22724.22
A8: Inventory (merchandise at cost) | B8: inventory | C8: 349578.53 | D8: 511975.69 | E8: 678710.31 | F8: 579158.97 | G8: 390873.1 | H8: 317051.88 | I8: 316752.7 | J8: 332144.87 | K8: 389634.13 | L8: 371878.78 | M8: 368673.68 | N8: 410467.71 | O8: 443372.09 | P8: 426880.82 | Q8: 420183.86 | R8: 311582.46 | S8: 234560.28 | T8: 238496.44 | U8: 287015.18 | V8: 266654.04 | W8: 307577.71 | X8: 379861.45 | Y8: 381919.76 | Z8: 415275.11 | AA8: 420900.66 | AB8: 504446.16 | AC8: 652730.09 | AD8: 589924.94 | AE8: 405109.75 | AF8: 317073.75 | AG8: 302597.06 | AH8: 277538.02 | AI8: 342554.88 | AJ8: =N8 -> 410467.71 | AK8: =Z8 -> 415275.11 | AL8: =AI8 -> 342554.88
A9: Service work in progress | B9: wip | C9: 1793.49 | D9: 1416.61 | E9: 4766.22 | F9: 4914.05 | G9: 9206.33 | H9: 17678.89 | I9: 13983.06 | J9: 8549.32 | K9: 2393.71 | L9: 4179.17 | M9: 2360.68 | N9: 1715.1 | O9: 2074.74 | P9: 3262.13 | Q9: 3723.83 | R9: 4559.47 | S9: 13663.06 | T9: 12230.34 | U9: 10213.1 | V9: 7557.49 | W9: 2282.79 | X9: 2091.4 | Y9: 1831.21 | Z9: 900.16 | AA9: 1666.38 | AB9: 3466.25 | AC9: 6124.01 | AD9: 9625.83 | AE9: 7544.97 | AF9: 7199.53 | AG9: 4844.33 | AH9: 3495.83 | AI9: 8663.8 | AJ9: =N9 -> 1715.1 | AK9: =Z9 -> 900.16 | AL9: =AI9 -> 8663.8
A10: Prepaid expenses & supplier deposits | B10: prepaid | C10: 67068.22 | D10: 90541.2 | E10: 49235.91 | F10: 23228.28 | G10: 45315.17 | H10: 50719.8 | I10: 42163.42 | J10: 24296.9 | K10: 30409.71 | L10: 30761.11 | M10: 19975.86 | N10: 7737.92 | O10: 28726.31 | P10: 31519.92 | Q10: 30623.93 | R10: 44688.34 | S10: 59009.97 | T10: 64979.97 | U10: 44001.39 | V10: 40703.94 | W10: 28436.75 | X10: 15388.58 | Y10: 13341.52 | Z10: 8391.91 | AA10: 29295.79 | AB10: 78577.47 | AC10: 62720.21 | AD10: 33843.06 | AE10: 40373.58 | AF10: 39044.55 | AG10: 54626.01 | AH10: 59665.51 | AI10: 26792.86 | AJ10: =N10 -> 7737.92 | AK10: =Z10 -> 8391.91 | AL10: =AI10 -> 26792.86
A11: Sales tax recoverable | B11: gst_rec | C11: 5902.66 | D11: 13605.71 | E11: 20971.92 | F11: 0 | G11: 0 | H11: 0 | I11: 0 | J11: 0 | K11: 0 | L11: 0 | M11: 0 | N11: 0 | O11: 1449.94 | P11: 391.43 | Q11: 0 | R11: 0 | S11: 0 | T11: 0 | U11: 0 | V11: 0 | W11: 0 | X11: 2090.55 | Y11: 1344.83 | Z11: 2913.21 | AA11: 0 | AB11: 4288.16 | AC11: 9828.12 | AD11: 0 | AE11: 0 | AF11: 0 | AG11: 0 | AH11: 0 | AI11: 0 | AJ11: =N11 -> 0 | AK11: =Z11 -> 2913.21 | AL11: =AI11 -> 0
A12: Total current assets | B12: current_assets | C12: =C6+C7+C8+C9+C10+C11 -> 717281.35 | D12: =D6+D7+D8+D9+D10+D11 -> 698983.42 | E12: =E6+E7+E8+E9+E10+E11 -> 859127.01 | F12: =F6+F7+F8+F9+F10+F11 -> 743214.22 | G12: =G6+G7+G8+G9+G10+G11 -> 683104.07 | H12: =H6+H7+H8+H9+H10+H11 -> 799047.3 | I12: =I6+I7+I8+I9+I10+I11 -> 858017.97 | J12: =J6+J7+J8+J9+J10+J11 -> 843432.36 | ... AI12: =AI6+AI7+AI8+AI9+AI10+AI11 -> 755195.2 | AJ12: =N12 -> 670576.54 | AK12: =Z12 -> 594159.29 | AL12: =AI12 -> 755195.2
A13: Property, plant and equipment (cost) | B13: ppe_gross | C13: 225000 | D13: 225000 | E13: 225000 | F13: 239500 | G13: 239500 | H13: 239500 | I13: 239500 | J13: 239500 | K13: 239500 | L13: 239500 | M13: 239500 | N13: 239500 | O13: 239500 | P13: 239500 | Q13: 249300 | R13: 249300 | S13: 255800 | T13: 255800 | U13: 255800 | V13: 255800 | W13: 255800 | X13: 255800 | Y13: 255800 | Z13: 255800 | AA13: 255800 | AB13: 273800 | AC13: 273800 | AD13: 281000 | AE13: 281000 | AF13: 281000 | AG13: 281000 | AH13: 281000 | AI13: 281000 | AJ13: =N13 -> 239500 | AK13: =Z13 -> 255800 | AL13: =AI13 -> 281000
A14: Accumulated depreciation | B14: acc_dep | C14: -7858.32 | D14: -10477.76 | E14: -13097.2 | F14: -15716.64 | G14: -18577.75 | H14: -21438.86 | I14: -24299.97 | J14: -27161.08 | K14: -30022.19 | L14: -32883.3 | M14: -35744.41 | N14: -38605.52 | O14: -41466.63 | P14: -44327.74 | Q14: -47188.85 | R14: -50213.29 | S14: -53237.73 | T14: -56329.88 | U14: -59422.03 | V14: -62514.18 | W14: -65606.33 | X14: -68698.48 | Y14: -71790.63 | Z14: -74882.78 | AA14: -77974.93 | AB14: -81067.08 | AC14: -84659.23 | AD14: -88251.38 | AE14: -91963.53 | AF14: -95675.68 | AG14: -99387.83 | AH14: -103099.98 | AI14: -106812.13 | AJ14: =N14 -> -38605.52 | AK14: =Z14 -> -74882.78 | AL14: =AI14 -> -106812.13
A15: Net property, plant and equipment | B15: ppe_net | C15: =C13+C14 -> 217141.68 | D15: =D13+D14 -> 214522.24 | E15: =E13+E14 -> 211902.8 | F15: =F13+F14 -> 223783.36 | G15: =G13+G14 -> 220922.25 | H15: =H13+H14 -> 218061.14 | I15: =I13+I14 -> 215200.03 | J15: =J13+J14 -> 212338.92 | ... AI15: =AI13+AI14 -> 174187.87 | AJ15: =N15 -> 200894.48 | AK15: =Z15 -> 180917.22 | AL15: =AI15 -> 174187.87
A16: TOTAL ASSETS | B16: total_assets | C16: =C12+C15 -> 934423.03 | D16: =D12+D15 -> 913505.66 | E16: =E12+E15 -> 1071029.8 | F16: =F12+F15 -> 966997.58 | G16: =G12+G15 -> 904026.32 | H16: =H12+H15 -> 1017108.4 | I16: =I12+I15 -> 1073218 | J16: =J12+J15 -> 1055771.3 | ... AI16: =AI12+AI15 -> 929383.07 | AJ16: =N16 -> 871471.02 | AK16: =Z16 -> 775076.51 | AL16: =AI16 -> 929383.07
A17: Accounts payable | B17: ap | C17: 180473.32 | D17: 193542.84 | E17: 240289.51 | F17: 122941.61 | G17: 111706.03 | H17: 196427.37 | I17: 240966.06 | J17: 203069.93 | K17: 203469.97 | L17: 105502.26 | M17: 77963.23 | N17: 126138.6 | O17: 92846.18 | P17: 51533.56 | Q17: 78145.69 | R17: 150294.4 | S17: 201316.41 | T17: 259089.41 | U17: 281334.96 | V17: 192438.58 | W17: 185722.14 | X17: 161754.65 | Y17: 96434.1 | Z17: 103089.24 | AA17: 79602.46 | AB17: 146482 | AC17: 290567.47 | AD17: 138533.3 | AE17: 134215.12 | AF17: 214392.9 | AG17: 254120.63 | AH17: 196778.83 | AI17: 185924.9 | AJ17: =N17 -> 126138.6 | AK17: =Z17 -> 103089.24 | AL17: =AI17 -> 185924.9
A18: Accrued expenses (payroll & head office) | B18: accrued | C18: 15464.69 | D18: 15293.54 | E18: 18568.2 | F18: 25077.43 | G18: 26226.2 | H18: 25823.55 | I18: 25306.19 | J18: 26338.85 | K18: 24022.68 | L18: 20169.41 | M18: 17883.45 | N18: 17587.99 | O18: 17340.37 | P18: 16499.97 | Q18: 21417.41 | R18: 26948.38 | S18: 28635.65 | T18: 28442.33 | U18: 27720.71 | V18: 28275.91 | W18: 27522.31 | X18: 20353.15 | Y18: 19825.93 | Z18: 20198.92 | AA18: 20113.31 | AB18: 18984.99 | AC18: 21891.61 | AD18: 29618.55 | AE18: 31301.71 | AF18: 32504.65 | AG18: 31076.47 | AH18: 31501.87 | AI18: 30310.02 | AJ18: =N18 -> 17587.99 | AK18: =Z18 -> 20198.92 | AL18: =AI18 -> 30310.02
A19: Income taxes payable | B19: tax_payable | C19: 0 | D19: 0 | E19: 0 | F19: 0 | G19: 0 | H19: 0 | I19: 0 | J19: 108.16 | K19: 0 | L19: 0 | M19: 0 | N19: 0 | O19: 0 | P19: 0 | Q19: 0 | R19: 0 | S19: 0 | T19: 0 | U19: 0 | V19: 0 | W19: 0 | X19: 0 | Y19: 0 | Z19: 0 | AA19: 0 | AB19: 0 | AC19: 0 | AD19: 0 | AE19: 0 | AF19: 0 | AG19: 0 | AH19: 1997.92 | AI19: 0 | AJ19: =N19 -> 0 | AK19: =Z19 -> 0 | AL19: =AI19 -> 0
A20: Sales tax payable | B20: gst_pay | C20: 0 | D20: 0 | E20: 0 | F20: 8536.66 | G20: 23648.74 | H20: 31329.39 | I20: 5506.95 | J20: 9225.59 | K20: 9254.6 | L20: 2565.91 | M20: 3648.65 | N20: 2224.29 | O20: 0 | P20: 0 | Q20: 949.89 | R20: 10233.13 | S20: 18888.31 | T20: 23921.02 | U20: 2123.32 | V20: 8017.24 | W20: 9773.6 | X20: 0 | Y20: 0 | Z20: 0 | AA20: 429.72 | AB20: 0 | AC20: 0 | AD20: 6998.61 | AE20: 23196.42 | AF20: 34194.46 | AG20: 6367.58 | AH20: 12786.78 | AI20: 11736.86 | AJ20: =N20 -> 2224.29 | AK20: =Z20 -> 0 | AL20: =AI20 -> 11736.86
A21: Short-term borrowings - revolving line of credit | B21: revolver | C21: 0 | D21: 0 | E21: 133000 | F21: 115000 | G21: 0 | H21: 0 | I21: 0 | J21: 0 | K21: 0 | L21: 0 | M21: 0 | N21: 0 | O21: 0 | P21: 54000 | Q21: 54000 | R21: 0 | S21: 0 | T21: 0 | U21: 0 | V21: 0 | W21: 0 | X21: 0 | Y21: 0 | Z21: 0 | AA21: 0 | AB21: 159000 | AC21: 159000 | AD21: 204000 | AE21: 0 | AF21: 0 | AG21: 0 | AH21: 0 | AI21: 0 | AJ21: =N21 -> 0 | AK21: =Z21 -> 0 | AL21: =AI21 -> 0
A22: Current portion of long-term debt | B22: term_current | C22: 50000.04 | D22: 50000.04 | E22: 50000.04 | F22: 50000.04 | G22: 50000.04 | H22: 50000.04 | I22: 50000.04 | J22: 50000.04 | K22: 50000.04 | L22: 50000.04 | M22: 50000.04 | N22: 50000.04 | O22: 50000.04 | P22: 50000.04 | Q22: 50000.04 | R22: 50000.04 | S22: 50000.04 | T22: 50000.04 | U22: 50000.04 | V22: 50000.04 | W22: 50000.04 | X22: 50000.04 | Y22: 50000.04 | Z22: 50000.04 | AA22: 50000.04 | AB22: 50000.04 | AC22: 50000.04 | AD22: 50000.04 | AE22: 50000.04 | AF22: 50000.04 | AG22: 50000.04 | AH22: 50000.04 | AI22: 50000.04 | AJ22: =N22 -> 50000.04 | AK22: =Z22 -> 50000.04 | AL22: =AI22 -> 50000.04
A23: Total current liabilities | B23: current_liabilities | C23: =C17+C18+C19+C20+C21+C22 -> 245938.05 | D23: =D17+D18+D19+D20+D21+D22 -> 258836.42 | E23: =E17+E18+E19+E20+E21+E22 -> 441857.75 | F23: =F17+F18+F19+F20+F21+F22 -> 321555.74 | G23: =G17+G18+G19+G20+G21+G22 -> 211581.01 | H23: =H17+H18+H19+H20+H21+H22 -> 303580.35 | I23: =I17+I18+I19+I20+I21+I22 -> 321779.24 | J23: =J17+J18+J19+J20+J21+J22 -> 288742.57 | ... AI23: =AI17+AI18+AI19+AI20+AI21+AI22 -> 277971.82 | AJ23: =N23 -> 195950.92 | AK23: =Z23 -> 173288.2 | AL23: =AI23 -> 277971.82
A24: Long-term debt (non-current portion) | B24: term_lt | C24: 195833.29 | D24: 191666.62 | E24: 187499.95 | F24: 183333.28 | G24: 179166.61 | H24: 174999.94 | I24: 170833.27 | J24: 166666.6 | K24: 162499.93 | L24: 158333.26 | M24: 154166.59 | N24: 149999.92 | O24: 145833.25 | P24: 141666.58 | Q24: 137499.91 | R24: 133333.24 | S24: 129166.57 | T24: 124999.9 | U24: 120833.23 | V24: 116666.56 | W24: 112499.89 | X24: 108333.22 | Y24: 104166.55 | Z24: 99999.88 | AA24: 95833.21 | AB24: 91666.54 | AC24: 87499.87 | AD24: 83333.2 | AE24: 79166.53 | AF24: 74999.86 | AG24: 70833.19 | AH24: 66666.52 | AI24: 62499.85 | AJ24: =N24 -> 149999.92 | AK24: =Z24 -> 99999.88 | AL24: =AI24 -> 62499.85
A25: TOTAL LIABILITIES | B25: total_liabilities | C25: =C23+C24 -> 441771.34 | D25: =D23+D24 -> 450503.04 | E25: =E23+E24 -> 629357.7 | F25: =F23+F24 -> 504889.02 | G25: =G23+G24 -> 390747.62 | H25: =H23+H24 -> 478580.29 | I25: =I23+I24 -> 492612.51 | J25: =J23+J24 -> 455409.17 | ... AI25: =AI23+AI24 -> 340471.67 | AJ25: =N25 -> 345950.84 | AK25: =Z25 -> 273288.08 | AL25: =AI25 -> 340471.67
A26: Share capital / allocated corporate equity | B26: equity_cap | C26: 600000 | D26: 600000 | E26: 600000 | F26: 600000 | G26: 600000 | H26: 600000 | I26: 600000 | J26: 600000 | K26: 600000 | L26: 600000 | M26: 600000 | N26: 600000 | O26: 600000 | P26: 600000 | Q26: 600000 | R26: 600000 | S26: 600000 | T26: 600000 | U26: 600000 | V26: 600000 | W26: 600000 | X26: 600000 | Y26: 600000 | Z26: 600000 | AA26: 600000 | AB26: 600000 | AC26: 600000 | AD26: 600000 | AE26: 600000 | AF26: 600000 | AG26: 600000 | AH26: 600000 | AI26: 600000 | AJ26: =N26 -> 600000 | AK26: =Z26 -> 600000 | AL26: =AI26 -> 600000
A27: Retained earnings | B27: retained | C27: -63638.88 | D27: -63638.88 | E27: -63638.88 | F27: -63638.88 | G27: -63638.88 | H27: -63638.88 | I27: -63638.88 | J27: -63638.88 | K27: -63638.88 | L27: -63638.88 | M27: -63638.88 | N27: -74479.82 | O27: -74479.82 | P27: -74479.82 | Q27: -74479.82 | R27: -74479.82 | S27: -74479.82 | T27: -74479.82 | U27: -74479.82 | V27: -74479.82 | W27: -74479.82 | X27: -74479.82 | Y27: -74479.82 | Z27: -98211.57 | AA27: -98211.57 | AB27: -98211.57 | AC27: -98211.57 | AD27: -98211.57 | AE27: -98211.57 | AF27: -98211.57 | AG27: -98211.57 | AH27: -98211.57 | AI27: -98211.57 | AJ27: =N27 -> -74479.82 | AK27: =Z27 -> -98211.57 | AL27: =AI27 -> -98211.57
A28: Current period earnings | B28: cpe | C28: -43709.43 | D28: -73358.5 | E28: -94689.01 | F28: -74252.56 | G28: -23082.42 | H28: 2167.03 | I28: 44244.37 | J28: 64000.99 | K28: 59681.92 | L28: 44699.88 | M28: 17833.21 | N28: 0 | O28: -38374.59 | P28: -72102.62 | Q28: -90783.78 | R28: -60844.92 | S28: -18433.77 | T28: 16149.45 | U28: 37271.4 | V28: 64173.56 | W28: 70931.89 | X28: 51538.88 | Y28: 20857.74 | Z28: 0 | AA28: -33687.81 | AB28: -69990.31 | AC28: -82329.19 | AD28: -67560.79 | AE28: -7843.52 | AF28: 46381.11 | AG28: 80311.9 | AH28: 104900.24 | AI28: 87122.97 | AJ28: =N28 -> 0 | AK28: =Z28 -> 0 | AL28: =AI28 -> 87122.97
A29: TOTAL EQUITY | B29: total_equity | C29: =C26+C27+C28 -> 492651.69 | D29: =D26+D27+D28 -> 463002.62 | E29: =E26+E27+E28 -> 441672.11 | F29: =F26+F27+F28 -> 462108.56 | G29: =G26+G27+G28 -> 513278.7 | H29: =H26+H27+H28 -> 538528.15 | I29: =I26+I27+I28 -> 580605.49 | J29: =J26+J27+J28 -> 600362.11 | ... AI29: =AI26+AI27+AI28 -> 588911.4 | AJ29: =N29 -> 525520.18 | AK29: =Z29 -> 501788.43 | AL29: =AI29 -> 588911.4
A30: TOTAL LIABILITIES AND EQUITY | B30: total_le | C30: =C25+C29 -> 934423.03 | D30: =D25+D29 -> 913505.66 | E30: =E25+E29 -> 1071029.8 | F30: =F25+F29 -> 966997.58 | G30: =G25+G29 -> 904026.32 | H30: =H25+H29 -> 1017108.4 | I30: =I25+I29 -> 1073218 | J30: =J25+J29 -> 1055771.3 | ... AI30: =AI25+AI29 -> 929383.07 | AJ30: =N30 -> 871471.02 | AK30: =Z30 -> 775076.51 | AL30: =AI30 -> 929383.07
A31: Check: assets - liabilities - equity | B31: check | C31: =ROUND(C16-C30,2) -> 0 | D31: =ROUND(D16-D30,2) -> 0 | E31: =ROUND(E16-E30,2) -> 0 | F31: =ROUND(F16-F30,2) -> 0 | G31: =ROUND(G16-G30,2) -> 0 | H31: =ROUND(H16-H30,2) -> 0 | I31: =ROUND(I16-I30,2) -> 0 | J31: =ROUND(J16-J30,2) -> 0 | ... AI31: =ROUND(AI16-AI30,2) -> 0 | AJ31: =N31 -> 0 | AK31: =Z31 -> 0 | AL31: =AI31 -> 0

Sheet Hist_CF
A1: ⚠ SIMULATED FINANCIAL INFORMATION - illustrative Calgary management accounts, not Prairie Pulse E-Bikes' actual financials. Synthetic data generated for a VisiVault Analytics proof of concept (seed 20240101).
A2: Historical cash flow statements - indirect method (CAD)
A3: Monthly values from the general ledger; subtotal rows are live formulas. FY columns sum the months.
A5: Line | B5: Key | C5: 2024-01 | D5: 2024-02 | E5: 2024-03 | F5: 2024-04 | G5: 2024-05 | H5: 2024-06 | I5: 2024-07 | J5: 2024-08 | K5: 2024-09 | L5: 2024-10 | M5: 2024-11 | N5: 2024-12 | O5: 2025-01 | P5: 2025-02 | Q5: 2025-03 | R5: 2025-04 | S5: 2025-05 | T5: 2025-06 | U5: 2025-07 | V5: 2025-08 | W5: 2025-09 | X5: 2025-10 | Y5: 2025-11 | Z5: 2025-12 | AA5: 2026-01 | AB5: 2026-02 | AC5: 2026-03 | AD5: 2026-04 | AE5: 2026-05 | AF5: 2026-06 | AG5: 2026-07 | AH5: 2026-08 | AI5: 2026-09 | AJ5: FY2024 | AK5: FY2025 | AL5: YTD Sep-2026
A6: Net income | B6: net_income | C6: -43709.43 | D6: -29649.07 | E6: -21330.51 | F6: 20436.45 | G6: 51170.14 | H6: 25249.45 | I6: 42077.34 | J6: 19756.62 | K6: -4319.07 | L6: -14982.04 | M6: -26866.67 | N6: -28674.15 | O6: -38374.59 | P6: -33728.03 | Q6: -18681.16 | R6: 29938.86 | S6: 42411.15 | T6: 34583.22 | U6: 21121.95 | V6: 26902.16 | W6: 6758.33 | X6: -19393.01 | Y6: -30681.14 | Z6: -44589.49 | AA6: -33687.81 | AB6: -36302.5 | AC6: -12338.88 | AD6: 14768.4 | AE6: 59717.27 | AF6: 54224.63 | AG6: 33930.79 | AH6: 24588.34 | AI6: -17777.27 | AJ6: =SUM(C6:N6) -> -10840.94 | AK6: =SUM(O6:Z6) -> -23731.75 | AL6: =SUM(AA6:AI6) -> 87122.97
A7: Depreciation and amortization | B7: da | C7: 2619.44 | D7: 2619.44 | E7: 2619.44 | F7: 2619.44 | G7: 2861.11 | H7: 2861.11 | I7: 2861.11 | J7: 2861.11 | K7: 2861.11 | L7: 2861.11 | M7: 2861.11 | N7: 2861.11 | O7: 2861.11 | P7: 2861.11 | Q7: 2861.11 | R7: 3024.44 | S7: 3024.44 | T7: 3092.15 | U7: 3092.15 | V7: 3092.15 | W7: 3092.15 | X7: 3092.15 | Y7: 3092.15 | Z7: 3092.15 | AA7: 3092.15 | AB7: 3092.15 | AC7: 3592.15 | AD7: 3592.15 | AE7: 3712.15 | AF7: 3712.15 | AG7: 3712.15 | AH7: 3712.15 | AI7: 3712.15 | AJ7: =SUM(C7:N7) -> 33366.64 | AK7: =SUM(O7:Z7) -> 36277.26 | AL7: =SUM(AA7:AI7) -> 31929.35
A8: (Increase) decrease in accounts receivable | B8: d_ar | C8: -9664.48 | D8: 2102.55 | E8: 2890.1 | F8: -30615.38 | G8: -11745.99 | H8: 31318.21 | I8: -16677.78 | J8: -9377.93 | K8: 29117.81 | L8: -2230.99 | M8: -7096.52 | N8: 7107.94 | O8: 4476.42 | P8: 857.36 | Q8: 4882.22 | R8: -29343.24 | S8: -772.5 | T8: -19194.7 | U8: 25033.75 | V8: -9356.24 | W8: 19145.86 | X8: 10266.56 | Y8: 6477.67 | Z8: -10785.55 | AA8: 1768.15 | AB8: -2699.79 | AC8: -6737.6 | AD8: 365 | AE8: -10489.76 | AF8: -5087.71 | AG8: 7478.28 | AH8: -2235.77 | AI8: 8099.83 | AJ8: =SUM(C8:N8) -> -14872.46 | AK8: =SUM(O8:Z8) -> 1687.61 | AL8: =SUM(AA8:AI8) -> -9539.37
A9: (Increase) decrease in inventory | B9: d_inv | C9: -111880.6 | D9: -162397.16 | E9: -166734.62 | F9: 99551.34 | G9: 188285.87 | H9: 73821.22 | I9: 299.18 | J9: -15392.17 | K9: -57489.26 | L9: 17755.35 | M9: 3205.1 | N9: -41794.03 | O9: -32904.38 | P9: 16491.27 | Q9: 6696.96 | R9: 108601.4 | S9: 77022.18 | T9: -3936.16 | U9: -48518.74 | V9: 20361.14 | W9: -40923.67 | X9: -72283.74 | Y9: -2058.31 | Z9: -33355.35 | AA9: -5625.55 | AB9: -83545.5 | AC9: -148283.93 | AD9: 62805.15 | AE9: 184815.19 | AF9: 88036 | AG9: 14476.69 | AH9: 25059.04 | AI9: -65016.86 | AJ9: =SUM(C9:N9) -> -172769.78 | AK9: =SUM(O9:Z9) -> -4807.4 | AL9: =SUM(AA9:AI9) -> 72720.23
A10: Increase (decrease) in accounts payable | B10: d_ap | C10: 125197.24 | D10: 13069.52 | E10: 46746.67 | F10: -117347.9 | G10: -11235.58 | H10: 84721.34 | I10: 44538.69 | J10: -37896.13 | K10: 400.04 | L10: -97967.71 | M10: -27539.03 | N10: 48175.37 | O10: -33292.42 | P10: -41312.62 | Q10: 26612.13 | R10: 72148.71 | S10: 51022.01 | T10: 57773 | U10: 22245.55 | V10: -88896.38 | W10: -6716.44 | X10: -23967.49 | Y10: -65320.55 | Z10: 6655.14 | AA10: -23486.78 | AB10: 66879.54 | AC10: 144085.47 | AD10: -152034.17 | AE10: -4318.18 | AF10: 80177.78 | AG10: 39727.73 | AH10: -57341.8 | AI10: -10853.93 | AJ10: =SUM(C10:N10) -> 70862.52 | AK10: =SUM(O10:Z10) -> -23049.36 | AL10: =SUM(AA10:AI10) -> 82835.66
A11: Service work in progress | B11: d_wip | C11: -1793.49 | D11: 376.88 | E11: -3349.61 | F11: -147.83 | G11: -4292.28 | H11: -8472.56 | I11: 3695.83 | J11: 5433.74 | K11: 6155.61 | L11: -1785.46 | M11: 1818.49 | N11: 645.58 | O11: -359.64 | P11: -1187.39 | Q11: -461.7 | R11: -835.64 | S11: -9103.59 | T11: 1432.72 | U11: 2017.24 | V11: 2655.61 | W11: 5274.7 | X11: 191.39 | Y11: 260.19 | Z11: 931.05 | AA11: -766.22 | AB11: -1799.87 | AC11: -2657.76 | AD11: -3501.82 | AE11: 2080.86 | AF11: 345.44 | AG11: 2355.2 | AH11: 1348.5 | AI11: -5167.97 | AJ11: =SUM(C11:N11) -> -1715.1 | AK11: =SUM(O11:Z11) -> 814.94 | AL11: =SUM(AA11:AI11) -> -7763.64
A12: Prepaid expenses & supplier deposits | B12: d_prepaid | C12: -67068.22 | D12: -23472.98 | E12: 41305.29 | F12: 26007.63 | G12: -22086.89 | H12: -5404.63 | I12: 8556.38 | J12: 17866.52 | K12: -6112.81 | L12: -351.4 | M12: 10785.25 | N12: 12237.94 | O12: -20988.39 | P12: -2793.61 | Q12: 895.99 | R12: -14064.41 | S12: -14321.63 | T12: -5970 | U12: 20978.58 | V12: 3297.45 | W12: 12267.19 | X12: 13048.17 | Y12: 2047.06 | Z12: 4949.61 | AA12: -20903.88 | AB12: -49281.68 | AC12: 15857.26 | AD12: 28877.15 | AE12: -6530.52 | AF12: 1329.03 | AG12: -15581.46 | AH12: -5039.5 | AI12: 32872.65 | AJ12: =SUM(C12:N12) -> -7737.92 | AK12: =SUM(O12:Z12) -> -653.99 | AL12: =SUM(AA12:AI12) -> -18400.95
A13: Accrued payroll & due to head office | B13: d_accrued | C13: 15464.69 | D13: -171.15 | E13: 3274.66 | F13: 6509.23 | G13: 1148.77 | H13: -402.65 | I13: -517.36 | J13: 1032.66 | K13: -2316.17 | L13: -3853.27 | M13: -2285.96 | N13: -295.46 | O13: -247.62 | P13: -840.4 | Q13: 4917.44 | R13: 5530.97 | S13: 1687.27 | T13: -193.32 | U13: -721.62 | V13: 555.2 | W13: -753.6 | X13: -7169.16 | Y13: -527.22 | Z13: 372.99 | AA13: -85.61 | AB13: -1128.32 | AC13: 2906.62 | AD13: 7726.94 | AE13: 1683.16 | AF13: 1202.94 | AG13: -1428.18 | AH13: 425.4 | AI13: -1191.85 | AJ13: =SUM(C13:N13) -> 17587.99 | AK13: =SUM(O13:Z13) -> 2610.93 | AL13: =SUM(AA13:AI13) -> 10111.1
A14: Sales tax payable / recoverable | B14: d_gst | C14: -5902.66 | D14: -7703.05 | E14: -7366.21 | F14: 29508.58 | G14: 15112.08 | H14: 7680.65 | I14: -25822.44 | J14: 3718.64 | K14: 29.01 | L14: -6688.69 | M14: 1082.74 | N14: -1424.36 | O14: -3674.23 | P14: 1058.51 | Q14: 1341.32 | R14: 9283.24 | S14: 8655.18 | T14: 5032.71 | U14: -21797.7 | V14: 5893.92 | W14: 1756.36 | X14: -11864.15 | Y14: 745.72 | Z14: -1568.38 | AA14: 3342.93 | AB14: -4717.88 | AC14: -5539.96 | AD14: 16826.73 | AE14: 16197.81 | AF14: 10998.04 | AG14: -27826.88 | AH14: 6419.2 | AI14: -1049.92 | AJ14: =SUM(C14:N14) -> 2224.29 | AK14: =SUM(O14:Z14) -> -5137.5 | AL14: =SUM(AA14:AI14) -> 14650.07
A15: Income taxes payable | B15: d_tax | C15: 0 | D15: 0 | E15: 0 | F15: 0 | G15: 0 | H15: 0 | I15: 0 | J15: 108.16 | K15: -108.16 | L15: 0 | M15: 0 | N15: 0 | O15: 0 | P15: 0 | Q15: 0 | R15: 0 | S15: 0 | T15: 0 | U15: 0 | V15: 0 | W15: 0 | X15: 0 | Y15: 0 | Z15: 0 | AA15: 0 | AB15: 0 | AC15: 0 | AD15: 0 | AE15: 0 | AF15: 0 | AG15: 0 | AH15: 1997.92 | AI15: -1997.92 | AJ15: =SUM(C15:N15) -> 0 | AK15: =SUM(O15:Z15) -> 0 | AL15: =SUM(AA15:AI15) -> 0
A16: Other working capital adjustments | B16: other_wc | C16: =C11+C12+C13+C14+C15 -> -59299.68 | D16: =D11+D12+D13+D14+D15 -> -30970.3 | E16: =E11+E12+E13+E14+E15 -> 33864.13 | F16: =F11+F12+F13+F14+F15 -> 61877.61 | G16: =G11+G12+G13+G14+G15 -> -10118.32 | H16: =H11+H12+H13+H14+H15 -> -6599.19 | I16: =I11+I12+I13+I14+I15 -> -14087.59 | J16: =J11+J12+J13+J14+J15 -> 28159.72 | ... AI16: =AI11+AI12+AI13+AI14+AI15 -> 23464.99 | AJ16: =SUM(C16:N16) -> 10359.26 | AK16: =SUM(O16:Z16) -> -2365.62 | AL16: =SUM(AA16:AI16) -> -1403.42
A17: Net cash from operating activities | B17: cfo | C17: =C6+C7+C8+C9+C10+C16 -> -96737.51 | D17: =D6+D7+D8+D9+D10+D16 -> -205225.02 | E17: =E6+E7+E8+E9+E10+E16 -> -101944.79 | F17: =F6+F7+F8+F9+F10+F16 -> 36521.56 | G17: =G6+G7+G8+G9+G10+G16 -> 209217.23 | H17: =H6+H7+H8+H9+H10+H16 -> 211372.14 | I17: =I6+I7+I8+I9+I10+I16 -> 59010.95 | J17: =J6+J7+J8+J9+J10+J16 -> -11888.78 | ... AI17: =AI6+AI7+AI8+AI9+AI10+AI16 -> -58371.09 | AJ17: =SUM(C17:N17) -> -83894.76 | AK17: =SUM(O17:Z17) -> -15989.26 | AL17: =SUM(AA17:AI17) -> 263665.42
A18: Capital expenditures (leasehold & systems) | B18: capex | C18: 0 | D18: 0 | E18: 0 | F18: 0 | G18: 0 | H18: 0 | I18: 0 | J18: 0 | K18: 0 | L18: 0 | M18: 0 | N18: 0 | O18: 0 | P18: 0 | Q18: 0 | R18: 0 | S18: -6500 | T18: 0 | U18: 0 | V18: 0 | W18: 0 | X18: 0 | Y18: 0 | Z18: 0 | AA18: 0 | AB18: -18000 | AC18: 0 | AD18: 0 | AE18: 0 | AF18: 0 | AG18: 0 | AH18: 0 | AI18: 0 | AJ18: =SUM(C18:N18) -> 0 | AK18: =SUM(O18:Z18) -> -6500 | AL18: =SUM(AA18:AI18) -> -18000
A19: Equipment purchases | B19: equipment | C19: 0 | D19: 0 | E19: 0 | F19: -14500 | G19: 0 | H19: 0 | I19: 0 | J19: 0 | K19: 0 | L19: 0 | M19: 0 | N19: 0 | O19: 0 | P19: 0 | Q19: -9800 | R19: 0 | S19: 0 | T19: 0 | U19: 0 | V19: 0 | W19: 0 | X19: 0 | Y19: 0 | Z19: 0 | AA19: 0 | AB19: 0 | AC19: 0 | AD19: -7200 | AE19: 0 | AF19: 0 | AG19: 0 | AH19: 0 | AI19: 0 | AJ19: =SUM(C19:N19) -> -14500 | AK19: =SUM(O19:Z19) -> -9800 | AL19: =SUM(AA19:AI19) -> -7200
A20: Net cash used in investing activities | B20: cfi | C20: =C18+C19 -> 0 | D20: =D18+D19 -> 0 | E20: =E18+E19 -> 0 | F20: =F18+F19 -> -14500 | G20: =G18+G19 -> 0 | H20: =H18+H19 -> 0 | I20: =I18+I19 -> 0 | J20: =J18+J19 -> 0 | ... AI20: =AI18+AI19 -> 0 | AJ20: =SUM(C20:N20) -> -14500 | AK20: =SUM(O20:Z20) -> -16300 | AL20: =SUM(AA20:AI20) -> -25200
A21: New borrowings - revolving line of credit | B21: rev_draw | C21: 0 | D21: 0 | E21: 133000 | F21: 90000 | G21: 0 | H21: 0 | I21: 0 | J21: 0 | K21: 0 | L21: 0 | M21: 0 | N21: 0 | O21: 0 | P21: 54000 | Q21: 0 | R21: 0 | S21: 0 | T21: 0 | U21: 0 | V21: 0 | W21: 0 | X21: 0 | Y21: 0 | Z21: 0 | AA21: 0 | AB21: 159000 | AC21: 0 | AD21: 128000 | AE21: 0 | AF21: 0 | AG21: 0 | AH21: 0 | AI21: 0 | AJ21: =SUM(C21:N21) -> 223000 | AK21: =SUM(O21:Z21) -> 54000 | AL21: =SUM(AA21:AI21) -> 287000
A22: Repayments - revolving line of credit | B22: rev_repay | C22: 0 | D22: 0 | E22: 0 | F22: -108000 | G22: -115000 | H22: 0 | I22: 0 | J22: 0 | K22: 0 | L22: 0 | M22: 0 | N22: 0 | O22: 0 | P22: 0 | Q22: 0 | R22: -54000 | S22: 0 | T22: 0 | U22: 0 | V22: 0 | W22: 0 | X22: 0 | Y22: 0 | Z22: 0 | AA22: 0 | AB22: 0 | AC22: 0 | AD22: -83000 | AE22: -204000 | AF22: 0 | AG22: 0 | AH22: 0 | AI22: 0 | AJ22: =SUM(C22:N22) -> -223000 | AK22: =SUM(O22:Z22) -> -54000 | AL22: =SUM(AA22:AI22) -> -287000
A23: Term loan repayments | B23: term_repay | C23: -4166.67 | D23: -4166.67 | E23: -4166.67 | F23: -4166.67 | G23: -4166.67 | H23: -4166.67 | I23: -4166.67 | J23: -4166.67 | K23: -4166.67 | L23: -4166.67 | M23: -4166.67 | N23: -4166.67 | O23: -4166.67 | P23: -4166.67 | Q23: -4166.67 | R23: -4166.67 | S23: -4166.67 | T23: -4166.67 | U23: -4166.67 | V23: -4166.67 | W23: -4166.67 | X23: -4166.67 | Y23: -4166.67 | Z23: -4166.67 | AA23: -4166.67 | AB23: -4166.67 | AC23: -4166.67 | AD23: -4166.67 | AE23: -4166.67 | AF23: -4166.67 | AG23: -4166.67 | AH23: -4166.67 | AI23: -4166.67 | AJ23: =SUM(C23:N23) -> -50000.04 | AK23: =SUM(O23:Z23) -> -50000.04 | AL23: =SUM(AA23:AI23) -> -37500.03
A24: Capital contributions from head office | B24: contrib | C24: 0 | D24: 0 | E24: 0 | F24: 0 | G24: 0 | H24: 0 | I24: 0 | J24: 0 | K24: 0 | L24: 0 | M24: 0 | N24: 0 | O24: 0 | P24: 0 | Q24: 0 | R24: 0 | S24: 0 | T24: 0 | U24: 0 | V24: 0 | W24: 0 | X24: 0 | Y24: 0 | Z24: 0 | AA24: 0 | AB24: 0 | AC24: 0 | AD24: 0 | AE24: 0 | AF24: 0 | AG24: 0 | AH24: 0 | AI24: 0 | AJ24: =SUM(C24:N24) -> 0 | AK24: =SUM(O24:Z24) -> 0 | AL24: =SUM(AA24:AI24) -> 0
A25: Distributions to head office | B25: dist | C25: 0 | D25: 0 | E25: 0 | F25: 0 | G25: 0 | H25: 0 | I25: 0 | J25: 0 | K25: 0 | L25: 0 | M25: 0 | N25: 0 | O25: 0 | P25: 0 | Q25: 0 | R25: 0 | S25: 0 | T25: 0 | U25: 0 | V25: 0 | W25: 0 | X25: 0 | Y25: 0 | Z25: 0 | AA25: 0 | AB25: 0 | AC25: 0 | AD25: 0 | AE25: 0 | AF25: 0 | AG25: 0 | AH25: 0 | AI25: 0 | AJ25: =SUM(C25:N25) -> 0 | AK25: =SUM(O25:Z25) -> 0 | AL25: =SUM(AA25:AI25) -> 0
A26: Net cash from (used in) financing activities | B26: cff | C26: =C21+C22+C23+C24+C25 -> -4166.67 | D26: =D21+D22+D23+D24+D25 -> -4166.67 | E26: =E21+E22+E23+E24+E25 -> 128833.33 | F26: =F21+F22+F23+F24+F25 -> -22166.67 | G26: =G21+G22+G23+G24+G25 -> -119166.67 | H26: =H21+H22+H23+H24+H25 -> -4166.67 | I26: =I21+I22+I23+I24+I25 -> -4166.67 | J26: =J21+J22+J23+J24+J25 -> -4166.67 | ... AI26: =AI21+AI22+AI23+AI24+AI25 -> -4166.67 | AJ26: =SUM(C26:N26) -> -50000.04 | AK26: =SUM(O26:Z26) -> -50000.04 | AL26: =SUM(AA26:AI26) -> -37500.03
A27: Net change in cash | B27: net_change | C27: =C17+C20+C26 -> -100904.18 | D27: =D17+D20+D26 -> -209391.69 | E27: =E17+E20+E26 -> 26888.54 | F27: =F17+F20+F26 -> -145.11 | G27: =G17+G20+G26 -> 90050.56 | H27: =H17+H20+H26 -> 207205.47 | I27: =I17+I20+I26 -> 54844.28 | J27: =J17+J20+J26 -> -16055.45 | ... AI27: =AI17+AI20+AI26 -> -62537.76 | AJ27: =SUM(C27:N27) -> -148394.8 | AK27: =SUM(O27:Z27) -> -82289.3 | AL27: =SUM(AA27:AI27) -> 200965.39
A28: Opening cash | B28: open_cash | C28: 384178.15 | D28: =C29 -> 283273.97 | E28: =D29 -> 73882.28 | F28: =E29 -> 100770.82 | G28: =F29 -> 100625.71 | H28: =G29 -> 190676.27 | I28: =H29 -> 397881.74 | J28: =I29 -> 452726.02 | K28: =J29 -> 436670.57 | ... AI28: =AH29 -> 416997.2 | AJ28: =C28 -> 384178.15 | AK28: =O28 -> 235783.35 | AL28: =AA28 -> 153494.05
A29: Closing cash (cash flow statement) | B29: close_cash | C29: =C28+C27 -> 283273.97 | D29: =D28+D27 -> 73882.28 | E29: =E28+E27 -> 100770.82 | F29: =F28+F27 -> 100625.71 | G29: =G28+G27 -> 190676.27 | H29: =H28+H27 -> 397881.74 | I29: =I28+I27 -> 452726.02 | J29: =J28+J27 -> 436670.57 | ... AI29: =AI28+AI27 -> 354459.44 | AJ29: =N29 -> 235783.35 | AK29: =Z29 -> 153494.05 | AL29: =AI29 -> 354459.44
A30: Cash per balance sheet | B30: bs_cash | C30: =Hist_BS!C6 -> 283273.97 | D30: =Hist_BS!D6 -> 73882.28 | E30: =Hist_BS!E6 -> 100770.82 | F30: =Hist_BS!F6 -> 100625.71 | G30: =Hist_BS!G6 -> 190676.27 | H30: =Hist_BS!H6 -> 397881.74 | I30: =Hist_BS!I6 -> 452726.02 | J30: =Hist_BS!J6 -> 436670.57 | ... AI30: =Hist_BS!AI6 -> 354459.44 | AJ30: =N30 -> 235783.35 | AK30: =Z30 -> 153494.05 | AL30: =AI30 -> 354459.44
A31: Check: closing cash - balance-sheet cash | B31: check | C31: =ROUND(C29-C30,2) -> 0 | D31: =ROUND(D29-D30,2) -> 0 | E31: =ROUND(E29-E30,2) -> 0 | F31: =ROUND(F29-F30,2) -> 0 | G31: =ROUND(G29-G30,2) -> 0 | H31: =ROUND(H29-H30,2) -> 0 | I31: =ROUND(I29-I30,2) -> 0 | J31: =ROUND(J29-J30,2) -> 0 | ... AI31: =ROUND(AI29-AI30,2) -> 0 | AJ31: =N31 -> 0 | AK31: =Z31 -> 0 | AL31: =AI31 -> 0

Sheet Hist_Balances
A1: ⚠ SIMULATED FINANCIAL INFORMATION - illustrative Calgary management accounts, not Prairie Pulse E-Bikes' actual financials. Synthetic data generated for a VisiVault Analytics proof of concept (seed 20240101).
A2: Month-end account balances from the general ledger (debit +, credit -)
A3: Post-closing at year ends. Each column must sum to zero (trial balance).
A5: Account | B5: Name | C5: 2023-12 | D5: 2024-01 | E5: 2024-02 | F5: 2024-03 | G5: 2024-04 | H5: 2024-05 | I5: 2024-06 | J5: 2024-07 | K5: 2024-08 | L5: 2024-09 | M5: 2024-10 | N5: 2024-11 | O5: 2024-12 | P5: 2025-01 | Q5: 2025-02 | R5: 2025-03 | S5: 2025-04 | T5: 2025-05 | U5: 2025-06 | V5: 2025-07 | W5: 2025-08 | X5: 2025-09 | Y5: 2025-10 | Z5: 2025-11 | AA5: 2025-12 | AB5: 2026-01 | AC5: 2026-02 | AD5: 2026-03 | AE5: 2026-04 | AF5: 2026-05 | AG5: 2026-06 | AH5: 2026-07 | AI5: 2026-08 | AJ5: 2026-09
A6: 1000 | B6: Cash - operating bank account | C6: 384178.15 | D6: 283273.97 | E6: 73882.28 | F6: 100770.82 | G6: 100625.71 | H6: 190676.27 | I6: 397881.74 | J6: 452726.02 | K6: 436670.57 | L6: 400722.01 | M6: 289312.24 | N6: 241110.08 | O6: 235783.35 | P6: 109112.94 | Q6: 100352.47 | R6: 115450.11 | S6: 241567.77 | T6: 390525.61 | U6: 458978.56 | V6: 478263.05 | W6: 438601.39 | X6: 434335.6 | Y6: 322089.65 | Z6: 231958.55 | AA6: 153494.05 | AB6: 72974.76 | AC6: 100304.24 | AD6: 87020.94 | AE6: 100079.8 | AF6: 138781.11 | AG6: 369552.74 | AH6: 422230.39 | AI6: 416997.2 | AJ6: 354459.44
A7: 1100 | B7: Card & debit processor settlements receivable | C7: 0 | D7: 6011.42 | E7: 6079.2 | F7: 778.02 | G7: 24424.63 | H7: 21719.28 | I7: 4303.42 | J7: 28088.37 | K7: 17785.72 | L7: 11413.96 | M7: 11003.07 | N7: 12760.16 | O7: 5502.49 | P7: 8886.03 | Q7: 7888.69 | R7: 1836.55 | S7: 20615.76 | T7: 19531.73 | U7: 26304.55 | V7: 11780.97 | W7: 13136.96 | X7: 9645.09 | Y7: 4239.31 | Z7: 701.12 | AA7: 11229.61 | AB7: 8783.89 | AC7: 4528.41 | AD7: 5440.15 | AE7: 14957.13 | AF7: 15569.58 | AG7: 25426.66 | AH7: 15443.31 | AI7: 14067.56 | AJ7: 13241.55
A8: 1110 | B8: Consumer-financing partner receivable | C8: 0 | D8: 2765.69 | E8: 0 | F8: 0 | G8: 10099.95 | H8: 14741.41 | I8: 7423.15 | J8: 0 | K8: 22506.97 | L8: 0 | M8: 3001.94 | N8: 7696.88 | O8: 0 | P8: 0 | Q8: 0 | R8: 0 | S8: 11485.41 | T8: 11873.38 | U8: 19506.66 | V8: 0 | W8: 16594.23 | X8: 7031.94 | Y8: 2471.69 | Z8: 0 | AA8: 0 | AB8: 0 | AC8: 3742.21 | AD8: 5976.04 | AE8: 2550.44 | AF8: 7924.45 | AG8: 4456.83 | AH8: 9472.67 | AI8: 13623.78 | AJ8: 6713.68
A9: 1120 | B9: Trade receivables - business/fleet accounts | C9: 0 | D9: 0 | E9: 0 | F9: 2971.48 | G9: 0 | H9: 9555.66 | I9: 3072.7 | J9: 2833.95 | K9: 0 | L9: 0 | M9: 0 | N9: 0 | O9: 8593.18 | P9: 178.49 | Q9: 0 | R9: 0 | S9: 0 | T9: 0 | U9: 4879.32 | V9: 14415.41 | W9: 6615.24 | X9: 0 | Y9: 0 | Z9: 0 | AA9: 0 | AB9: 0 | AC9: 3006.13 | AD9: 7435.43 | AE9: 0 | AF9: 5051.41 | AG9: 2922.77 | AH9: 0 | AI9: 103.95 | AJ9: 10.49
A10: 1130 | B10: Manufacturer warranty claims receivable | C10: 0 | D10: 887.37 | E10: 1482.73 | F10: 922.33 | G10: 762.63 | H10: 1016.85 | I10: 915.72 | J10: 1470.45 | K10: 1478.01 | L10: 1238.93 | M10: 878.87 | N10: 1523.36 | O10: 776.79 | P10: 1331.52 | Q10: 1649.99 | R10: 2819.91 | S10: 1898.53 | T10: 3367.09 | U10: 3276.37 | V10: 2736.77 | W10: 1942.96 | X10: 2466.5 | Y10: 2165.97 | Z10: 1698.18 | AA10: 1955.24 | AB10: 2632.81 | AC10: 2839.74 | AD10: 2002.47 | AE10: 2981.52 | AF10: 2433.41 | AG10: 3260.3 | AH10: 3672.3 | AI10: 3028.76 | AJ10: 2758.5
A11: 1200 | B11: Merchandise inventory (standard cost) | C11: 237697.93 | D11: 349578.53 | E11: 511975.69 | F11: 678710.31 | G11: 579158.97 | H11: 390873.1 | I11: 317051.88 | J11: 316752.7 | K11: 332144.87 | L11: 389634.13 | M11: 371878.78 | N11: 368673.68 | O11: 410467.71 | P11: 443372.09 | Q11: 426880.82 | R11: 420183.86 | S11: 311582.46 | T11: 234560.28 | U11: 238496.44 | V11: 287015.18 | W11: 266654.04 | X11: 307577.71 | Y11: 379861.45 | Z11: 381919.76 | AA11: 415275.11 | AB11: 420900.66 | AC11: 504446.16 | AD11: 652730.09 | AE11: 589924.94 | AF11: 405109.75 | AG11: 317073.75 | AH11: 302597.06 | AI11: 277538.02 | AJ11: 342554.88
A12: 1250 | B12: Service work in progress | C12: 0 | D12: 1793.49 | E12: 1416.61 | F12: 4766.22 | G12: 4914.05 | H12: 9206.33 | I12: 17678.89 | J12: 13983.06 | K12: 8549.32 | L12: 2393.71 | M12: 4179.17 | N12: 2360.68 | O12: 1715.1 | P12: 2074.74 | Q12: 3262.13 | R12: 3723.83 | S12: 4559.47 | T12: 13663.06 | U12: 12230.34 | V12: 10213.1 | W12: 7557.49 | X12: 2282.79 | Y12: 2091.4 | Z12: 1831.21 | AA12: 900.16 | AB12: 1666.38 | AC12: 3466.25 | AD12: 6124.01 | AE12: 9625.83 | AF12: 7544.97 | AG12: 7199.53 | AH12: 4844.33 | AI12: 3495.83 | AJ12: 8663.8
A13: 1300 | B13: Prepaid insurance | C13: 0 | D13: 25300 | E13: 23000 | F13: 20700 | G13: 18400 | H13: 16100 | I13: 13800 | J13: 11500 | K13: 9200 | L13: 6900 | M13: 4600 | N13: 2300 | O13: 0 | P13: 26312 | Q13: 23920 | R13: 21528 | S13: 19136 | T13: 16744 | U13: 14352 | V13: 11960 | W13: 9568 | X13: 7176 | Y13: 4784 | Z13: 2392 | AA13: 0 | AB13: 27364.48 | AC13: 24876.8 | AD13: 22389.12 | AE13: 19901.44 | AF13: 17413.76 | AG13: 14926.08 | AH13: 12438.4 | AI13: 9950.72 | AJ13: 7463.04
A14: 1310 | B14: Supplier deposits on open purchase orders | C14: 0 | D14: 41768.22 | E14: 67541.2 | F14: 28535.91 | G14: 4828.28 | H14: 29215.17 | I14: 36919.8 | J14: 30663.42 | K14: 15096.9 | L14: 23509.71 | M14: 26161.11 | N14: 17675.86 | O14: 7737.92 | P14: 2414.31 | Q14: 7599.92 | R14: 9095.93 | S14: 25552.34 | T14: 42265.97 | U14: 50627.97 | V14: 32041.39 | W14: 31135.94 | X14: 21260.75 | Y14: 10604.58 | Z14: 10949.52 | AA14: 8391.91 | AB14: 1931.31 | AC14: 53700.67 | AD14: 40331.09 | AE14: 13941.62 | AF14: 22959.82 | AG14: 24118.47 | AH14: 42187.61 | AI14: 49714.79 | AJ14: 19329.82
A15: 1400 | B15: GST input tax credits (ITCs) | C15: 0 | D15: 9984.44 | E15: 22811.88 | F15: 38532.81 | G15: 9342.71 | H15: 15785.34 | I15: 26495.09 | J15: 14634.04 | K15: 28053.51 | L15: 39413.89 | M15: 6242.52 | N15: 12234.88 | O15: 20450.16 | P15: 5906.67 | Q15: 9210.67 | R15: 14798.39 | S15: 8575.14 | T15: 20450.18 | U15: 35883.44 | V15: 16279.98 | W15: 28707.75 | X15: 40733.3 | Y15: 10179.57 | Z15: 16503.78 | AA15: 22995.08 | AB15: 5392.38 | AC15: 15464.75 | AD15: 31197.98 | AE15: 10424.87 | AF15: 18807.76 | AG15: 30778 | AH15: 13766.3 | AI15: 26406.79 | AJ15: 38811.25
A16: 1500 | B16: Leasehold improvements | C16: 165000 | D16: 165000 | E16: 165000 | F16: 165000 | G16: 165000 | H16: 165000 | I16: 165000 | J16: 165000 | K16: 165000 | L16: 165000 | M16: 165000 | N16: 165000 | O16: 165000 | P16: 165000 | Q16: 165000 | R16: 165000 | S16: 165000 | T16: 171500 | U16: 171500 | V16: 171500 | W16: 171500 | X16: 171500 | Y16: 171500 | Z16: 171500 | AA16: 171500 | AB16: 171500 | AC16: 171500 | AD16: 171500 | AE16: 171500 | AF16: 171500 | AG16: 171500 | AH16: 171500 | AI16: 171500 | AJ16: 171500
A17: 1510 | B17: Workshop equipment & racking | C17: 38000 | D17: 38000 | E17: 38000 | F17: 38000 | G17: 52500 | H17: 52500 | I17: 52500 | J17: 52500 | K17: 52500 | L17: 52500 | M17: 52500 | N17: 52500 | O17: 52500 | P17: 52500 | Q17: 52500 | R17: 62300 | S17: 62300 | T17: 62300 | U17: 62300 | V17: 62300 | W17: 62300 | X17: 62300 | Y17: 62300 | Z17: 62300 | AA17: 62300 | AB17: 62300 | AC17: 62300 | AD17: 62300 | AE17: 69500 | AF17: 69500 | AG17: 69500 | AH17: 69500 | AI17: 69500 | AJ17: 69500
... A59: 8000 | B59: Income tax expense (allocated) | C59: 0 | D59: 0 | E59: 0 | F59: 0 | G59: 0 | H59: 0 | I59: 0 | J59: 0 | K59: 108.16 | L59: 0 | M59: 0 | N59: 0 | O59: 0 | P59: 0 | Q59: 0 | R59: 0 | S59: 0 | T59: 0 | U59: 0 | V59: 0 | W59: 0 | X59: 0 | Y59: 0 | Z59: 0 | AA59: 0 | AB59: 0 | AC59: 0 | AD59: 0 | AE59: 0 | AF59: 0 | AG59: 0 | AH59: 0 | AI59: 1997.92 | AJ59: 0
B60: Check: sum of balances (must be 0) | C60: =ROUND(SUM(C6:C59),2) -> 0 | D60: =ROUND(SUM(D6:D59),2) -> 0 | E60: =ROUND(SUM(E6:E59),2) -> 0 | F60: =ROUND(SUM(F6:F59),2) -> 0 | G60: =ROUND(SUM(G6:G59),2) -> 0 | H60: =ROUND(SUM(H6:H59),2) -> 0 | I60: =ROUND(SUM(I6:I59),2) -> 0 | J60: =ROUND(SUM(J6:J59),2) -> 0 | ... AJ60: =ROUND(SUM(AJ6:AJ59),2) -> 0
